async_fifo/async_fifo.sv
// Simple FWFT async fifo
// Restricted to depths of powers of 2

// FWFT behavior: oldest value already sitting on dout
// On first instance of ren && rclk, second-oldest value gets clocked out

module async_fifo #(
  parameter WIDTH = 16,
  parameter DEPTH = 4
)(
  input logic rclk, // read clock
  input logic wclk, // write clock
  input logic r_rst, // read domain reset
  input logic w_rst, // write domain reset
  input logic ren, // active low read enable
  input logic wen, // active low write enable
  input logic [WIDTH - 1:0] din, // data to write to fifo
  output logic [WIDTH - 1:0] dout, // data coming out of fifo
  output logic empty, // active high fifo empty flag
  output logic full // active high fifo full flag
);

  localparam POINTER_WIDTH = $clog2(DEPTH);

  logic [WIDTH - 1:0] fifo [DEPTH - 1:0]; // FIFO memory

  // intermediary signals
  // declared as POINTER_WIDTH in size because grey code requires extra MSB
  logic [POINTER_WIDTH:0] b_wptr; // binary write pointer
  logic [POINTER_WIDTH:0] b_rptr; // binary read pointer

  logic [POINTER_WIDTH:0] g_wptr; // gray code write pointer
  logic [POINTER_WIDTH:0] g_rptr; // gray code read pointer

  logic [POINTER_WIDTH:0] sync_g_wptr; // synchronized gray code write pointer
  logic [POINTER_WIDTH:0] sync_g_rptr; // synchronized gray code read pointer

  logic [POINTER_WIDTH:0] sync_g_wptr_inter; // intermediary signal in 2FF (Danger Zone!)
  logic [POINTER_WIDTH:0] sync_g_rptr_inter; // intermediary signal in 2FF (Danger Zone!)

  // empty flag asserted when synchronized write pointer equals read pointer
  assign empty = (sync_g_wptr == g_rptr);

  // full flag asserted when top two MSB of write pointer is the inverse of the top two MSB of read pointer
  // and if the rest of both are the same
  assign full = (sync_g_rptr[POINTER_WIDTH:POINTER_WIDTH-1] == ~g_wptr[POINTER_WIDTH:POINTER_WIDTH-1]) && (sync_g_rptr[POINTER_WIDTH-2:0] == g_wptr[POINTER_WIDTH-2:0]);

  // write pointer handler
  always_ff @(posedge wclk, negedge w_rst) begin
    if (~w_rst) begin
      b_wptr <= 0;
      g_wptr <= 0;

      // TODO: move this to synchronized reset block later
      for (int i = 0; i < DEPTH; i++) begin
        fifo[i] <= 0;
      end
    end else begin
      if (~wen && ~full) begin // if valid write condition
        // truncate write pointer to proper bit width
        b_wptr <= b_wptr + 1;
        g_wptr <= (b_wptr + 1) ^ ((b_wptr + 1) >> 1); // added 1 to b_wptr to account for non-blocking assignment
        fifo[b_wptr[POINTER_WIDTH - 1:0]] <= din;
      end
    end
  end

  // assign dout combinationally for FWFT behavior
  assign dout = fifo[b_rptr[POINTER_WIDTH - 1:0]];

  // read pointer handler
  always_ff @(posedge rclk, negedge r_rst) begin
    if (~r_rst) begin
      b_rptr <= 0;
      g_rptr <= 0;
    end else begin
      if (~ren && ~empty) begin // if valid read condition
        b_rptr <= b_rptr + 1;
        g_rptr <= (b_rptr + 1) ^ ((b_rptr + 1) >> 1);
      end
    end
  end

  // 2FF sync for rptr
  always_ff @(posedge wclk, negedge w_rst) begin
    if (~w_rst) begin
      sync_g_rptr_inter <= 0;
      sync_g_rptr <= 0;
    end else begin
      sync_g_rptr_inter <= g_rptr;
      sync_g_rptr <= sync_g_rptr_inter;
    end
  end

  // 2FF sync for wptr
  always_ff @(posedge rclk, negedge r_rst) begin
    if (~r_rst) begin
      sync_g_wptr_inter <= 0;
      sync_g_wptr <= 0;
    end else begin
      sync_g_wptr_inter <= g_wptr;
      sync_g_wptr <= sync_g_wptr_inter;
    end
  end

endmodule

async_fifo/tb_async_fifo.sv
// Testbench for async fifo
// Tests async FWFT behavior
// Depth restricted to powers of 2

`timescale 1ns/1ps

module tb_async_fifo;

  parameter WIDTH = 32;
  parameter DEPTH = 8;
  parameter TEST_LEN = 32;

  // 1. Declare local signals to connect to the Design Under Test (DUT)
  logic rclk; // read clock
  logic wclk; // write clock
  logic r_rst;
  logic w_rst;
  logic ren; // active low read enable
  logic wen; // active low write enable
  logic [WIDTH - 1:0] din; // data to write to fifo
  logic [WIDTH - 1:0] dout; // data coming out of fifo
  logic empty; // active high fifo empty flag
  logic full; // active high fifo full flag

  async_fifo #(WIDTH, DEPTH) dut (.*);

  // 3. Clock Generation
  // Generate two separate clocks for write and read
  initial begin
    wclk = 0;
    forever #3ns wclk = ~wclk;
  end

  initial begin
    rclk = 0;
    forever #13ns rclk = ~rclk;
  end

  // write driver
  // checks if fifo not full and writes to it
  task write_fifo(input logic [WIDTH-1:0] test_din);
    if (~full) begin // if not full, write
      wen = 0;
      din = test_din;
      @(posedge wclk);
      $display("[%dns] Wrote %d to FIFO!", $time, test_din);
    end else begin // if full, wait
      wen = 1;
      @(posedge wclk);
      $display("[%dns] Tried to write %d, but FIFO was full!", $time, test_din);
    end
  endtask

  // read driver
  // checks if fifo not empty and reads from it
  task read_fifo(output logic [WIDTH-1:0] test_dout);
    if (~empty) begin // if not empty, read
      ren = 0;
      test_dout = dout;
      @(posedge rclk);
      $display("[%dns] Read %D from FIFO!", $time, test_dout);
    end else begin // if empty, wait
      ren = 1;
      @(posedge rclk);
      $display("[%dns] Tried to read %d, but FIFO was empty!", $time, test_dout);
    end
  endtask

// 4. Stimulus Generation
  initial begin
    logic [WIDTH-1:0] test_data;
    logic [WIDTH-1:0] captured_data;

    logic [WIDTH-1:0] bs_input [TEST_LEN]; // TEST_LEN-long array of input bitstreams
    logic [WIDTH-1:0] bs_output [TEST_LEN]; // FIFO output
    int errors = 0;
    

    int random_w_delay;
    int random_r_delay;

    // initialize input bitstreams
    for (int i=0; i<TEST_LEN; i++) begin
      bs_input[i] = 32'h0000_0000 + i;
    end

    $dumpfile("dump.vcd");
    $dumpvars(0, tb_async_fifo);
    for (int i = 0; i < DEPTH; i = i + 1) begin
      $dumpvars(0, tb_async_fifo.dut.fifo[i]);
    end

    // Initialize inputs
    r_rst = 0;
    w_rst = 0;
    ren   = 1;
    wen   = 1;
    din   = 0;

    // Wait for slower read clock
    @(posedge rclk);
    @(posedge wclk);
    r_rst = 1;
    w_rst = 1;
    $display("--- Starting async FIFO Tests ---");

    test_data = 32'd100;

    // for (int i=0; i<TEST_LEN; i++) begin
    //   write_fifo(bs_input[i]);
    // end

    fork
      // Thread 1: Continuous Write Loop
      begin
        int w_idx = 0;
        while(w_idx < TEST_LEN) begin
          write_fifo(bs_input[w_idx]);
          if (~full) begin
            w_idx = w_idx + 1;
          end
        end
        $display("Write thread done!");
      end

      // Thread 2: Continuous Read Loop
      begin
        int r_idx = 0;
        logic [WIDTH-1:0] read_data;
        while(r_idx < TEST_LEN) begin
          read_fifo(read_data);
          if (~empty) begin
            bs_output[r_idx] = read_data;
            r_idx = r_idx + 1;
          end
        end
      end
    join

    // 5. Post-test Verification/Self-Checking
    $display("--- Analyzing Results ---");
    for (int i = 0; i < TEST_LEN; i++) begin
      if (bs_input[i] !== bs_output[i]) begin
        $display("ERROR at index %0d: Expected %d, Got %d", i, bs_input[i], bs_output[i]);
        errors++;
      end
    end

    if (errors == 0) begin
      $display("SUCCESS: All TEST_LEN bitstream elements matched perfectly!");
    end else begin
      $display("FAILURE: %0d mismatches detected.", errors);
    end

    $display("--- Tests Complete! ---");
    $finish;
  end

endmodule

async_fifo/dump.vcd
$date
	Thu Jun  4 00:31:14 2026
$end
$version
	Icarus Verilog
$end
$timescale
	1ps
$end
$scope module tb_async_fifo $end
$var wire 1 ! full $end
$var wire 1 " empty $end
$var wire 32 # dout [31:0] $end
$var parameter 32 $ DEPTH $end
$var parameter 32 % TEST_LEN $end
$var parameter 32 & WIDTH $end
$var reg 32 ' din [31:0] $end
$var reg 1 ( r_rst $end
$var reg 1 ) rclk $end
$var reg 1 * ren $end
$var reg 1 + w_rst $end
$var reg 1 , wclk $end
$var reg 1 - wen $end
$scope module dut $end
$var wire 32 . din [31:0] $end
$var wire 32 / dout [31:0] $end
$var wire 1 ! full $end
$var wire 1 ( r_rst $end
$var wire 1 ) rclk $end
$var wire 1 * ren $end
$var wire 1 + w_rst $end
$var wire 1 , wclk $end
$var wire 1 - wen $end
$var wire 1 " empty $end
$var parameter 32 0 DEPTH $end
$var parameter 32 1 POINTER_WIDTH $end
$var parameter 32 2 WIDTH $end
$var reg 4 3 b_rptr [3:0] $end
$var reg 4 4 b_wptr [3:0] $end
$var reg 4 5 g_rptr [3:0] $end
$var reg 4 6 g_wptr [3:0] $end
$var reg 4 7 sync_g_rptr [3:0] $end
$var reg 4 8 sync_g_rptr_inter [3:0] $end
$var reg 4 9 sync_g_wptr [3:0] $end
$var reg 4 : sync_g_wptr_inter [3:0] $end
$scope begin $ivl_for_loop0 $end
$var integer 32 ; i [31:0] $end
$upscope $end
$upscope $end
$scope begin $unm_blk_22 $end
$var reg 32 < test_data [31:0] $end
$var integer 32 = errors [31:0] $end
$scope begin $ivl_for_loop1 $end
$var integer 32 > i [31:0] $end
$upscope $end
$scope begin $ivl_for_loop2 $end
$var integer 32 ? i [31:0] $end
$upscope $end
$scope begin $ivl_for_loop3 $end
$var integer 32 @ i [31:0] $end
$upscope $end
$scope begin $unm_blk_26 $end
$var integer 32 A w_idx [31:0] $end
$upscope $end
$scope begin $unm_blk_29 $end
$var reg 32 B read_data [31:0] $end
$var integer 32 C r_idx [31:0] $end
$upscope $end
$upscope $end
$scope task read_fifo $end
$var reg 32 D test_dout [31:0] $end
$upscope $end
$scope task write_fifo $end
$var reg 32 E test_din [31:0] $end
$upscope $end
$upscope $end
$scope module tb_async_fifo $end
$scope module dut $end
$var reg 32 F \fifo[0] [31:0] $end
$upscope $end
$upscope $end
$scope module tb_async_fifo $end
$scope module dut $end
$var reg 32 G \fifo[1] [31:0] $end
$upscope $end
$upscope $end
$scope module tb_async_fifo $end
$scope module dut $end
$var reg 32 H \fifo[2] [31:0] $end
$upscope $end
$upscope $end
$scope module tb_async_fifo $end
$scope module dut $end
$var reg 32 I \fifo[3] [31:0] $end
$upscope $end
$upscope $end
$scope module tb_async_fifo $end
$scope module dut $end
$var reg 32 J \fifo[4] [31:0] $end
$upscope $end
$upscope $end
$scope module tb_async_fifo $end
$scope module dut $end
$var reg 32 K \fifo[5] [31:0] $end
$upscope $end
$upscope $end
$scope module tb_async_fifo $end
$scope module dut $end
$var reg 32 L \fifo[6] [31:0] $end
$upscope $end
$upscope $end
$scope module tb_async_fifo $end
$scope module dut $end
$var reg 32 M \fifo[7] [31:0] $end
$upscope $end
$upscope $end
$enddefinitions $end
$comment Show the parameter values. $end
$dumpall
b100000 2
b11 1
b1000 0
b100000 &
b100000 %
b1000 $
$end
#0
$dumpvars
b0 M
b0 L
b0 K
b0 J
b0 I
b0 H
b0 G
b0 F
bx E
bx D
b0 C
bx B
b0 A
b0 @
b1000 ?
b100000 >
b0 =
bx <
b1000 ;
b0 :
b0 9
b0 8
b0 7
b0 6
b0 5
b0 4
b0 3
b0 /
b0 .
1-
0,
0+
1*
0)
0(
b0 '
b0 #
1"
0!
$end
#3000
b0 M
b0 L
b0 K
b0 J
b0 I
b0 H
b0 G
b0 F
b1000 ;
1,
#6000
0,
#9000
b0 M
b0 L
b0 K
b0 J
b0 I
b0 H
b0 G
b0 F
b1000 ;
1,
#12000
0,
#13000
1)
#15000
b0 F
b1 6
b1 4
0-
b0 E
b1100100 <
1+
1(
1,
#18000
0,
#21000
b1 G
b11 6
b10 4
b1 '
b1 .
b1 E
b1 A
1,
#24000
0,
#26000
0)
#27000
b10 H
b10 6
b11 4
b10 '
b10 .
b10 E
b10 A
1,
#30000
0,
#33000
b11 I
b110 6
b100 4
b11 '
b11 .
b11 E
b11 A
1,
#36000
0,
#39000
b100 J
b111 6
b101 4
b110 :
b100 '
b100 .
b100 E
b100 A
1,
1)
#42000
0,
#45000
b101 K
b101 6
b110 4
b101 '
b101 .
b101 E
b101 A
1,
#48000
0,
#51000
b110 L
b100 6
b111 4
b110 '
b110 .
b110 E
b110 A
1,
#52000
0)
#54000
0,
#57000
1!
b111 M
b1100 6
b1000 4
b111 '
b111 .
b111 E
b111 A
1,
#60000
0,
#63000
1-
1,
#65000
0"
b110 9
b1100 :
1)
#66000
0,
#69000
1,
#72000
0,
#75000
1,
#78000
0,
0)
#81000
1,
#84000
0,
#87000
1,
#90000
0,
#91000
b1 #
b1 /
b1 5
b1 3
b1100 9
b0 D
0*
b1 C
1)
#93000
b1 8
1,
#96000
0,
#99000
0!
b1 7
1,
#102000
0,
#104000
0)
#105000
1!
b1000 F
b1101 6
b1001 4
b1000 '
b1000 .
0-
b1000 E
b1000 A
1,
#108000
0,
#111000
1-
1,
#114000
0,
#117000
b10 #
b10 /
b1101 :
b11 5
b10 3
b1 D
b10 C
b0 B
1,
1)
#120000
0,
#123000
b11 8
1,
#126000
0,
#129000
0!
b11 7
1,
#130000
0)
#132000
0,
#135000
1!
b1001 G
b1111 6
b1010 4
b1001 '
b1001 .
0-
b1001 E
b1001 A
1,
#138000
0,
#141000
1-
1,
#143000
b11 #
b11 /
b10 5
b11 3
b1101 9
b1111 :
b10 D
b11 C
b1 B
1)
#144000
0,
#147000
b10 8
1,
#150000
0,
#153000
0!
b10 7
1,
#156000
0,
0)
#159000
1!
b1010 H
b1110 6
b1011 4
b1010 '
b1010 .
0-
b1010 E
b1010 A
1,
#162000
0,
#165000
1-
1,
#168000
0,
#169000
b100 #
b100 /
b1111 9
b1110 :
b110 5
b100 3
b11 D
b100 C
b10 B
1)
#171000
b110 8
1,
#174000
0,
#177000
0!
b110 7
1,
#180000
0,
#182000
0)
#183000
1!
b1011 I
b1010 6
b1100 4
b1011 '
b1011 .
0-
b1011 E
b1011 A
1,
#186000
0,
#189000
1-
1,
#192000
0,
#195000
b101 #
b101 /
b111 5
b101 3
b1110 9
b1010 :
b100 D
b101 C
b11 B
1,
1)
#198000
0,
#201000
b111 8
1,
#204000
0,
#207000
0!
b111 7
1,
#208000
0)
#210000
0,
#213000
1!
b1100 J
b1011 6
b1101 4
b1100 '
b1100 .
0-
b1100 E
b1100 A
1,
#216000
0,
#219000
1-
1,
#221000
b110 #
b110 /
b1010 9
b1011 :
b101 5
b110 3
b101 D
b110 C
b100 B
1)
#222000
0,
#225000
b101 8
1,
#228000
0,
#231000
0!
b101 7
1,
#234000
0,
0)
#237000
1!
b1101 K
b1001 6
b1110 4
b1101 '
b1101 .
0-
b1101 E
b1101 A
1,
#240000
0,
#243000
1-
1,
#246000
0,
#247000
b111 #
b111 /
b100 5
b111 3
b1011 9
b1001 :
b110 D
b111 C
b101 B
1)
#249000
b100 8
1,
#252000
0,
#255000
0!
b100 7
1,
#258000
0,
#260000
0)
#261000
1!
b1110 L
b1000 6
b1111 4
b1110 '
b1110 .
0-
b1110 E
b1110 A
1,
#264000
0,
#267000
1-
1,
#270000
0,
#273000
b1000 #
b1000 /
b1001 9
b1000 :
b1100 5
b1000 3
b111 D
b1000 C
b110 B
1,
1)
#276000
0,
#279000
b1100 8
1,
#282000
0,
#285000
0!
b1100 7
1,
#286000
0)
#288000
0,
#291000
b1111 M
b0 4
b1111 '
b1111 .
0-
b1111 E
b1111 A
1,
#294000
0,
#297000
b10000 F
b10000 #
b10000 /
b1 6
b1 4
b10000 '
b10000 .
b10000 E
b10000 A
1,
#299000
b1001 #
b1001 /
b1101 5
b1001 3
b1000 9
b1 :
b10000 D
b1001 C
b111 B
1)
#300000
0,
#303000
b1101 8
b10001 G
b10001 #
b10001 /
b11 6
b10 4
b10001 '
b10001 .
b10001 E
b10001 A
1,
#306000
0,
#309000
b10010 H
b10 6
b11 4
b1101 7
b10010 '
b10010 .
b10010 E
b10010 A
1,
#312000
0,
0)
#315000
b10011 I
b110 6
b100 4
b10011 '
b10011 .
b10011 E
b10011 A
1,
#318000
0,
#321000
b10100 J
b111 6
b101 4
b10100 '
b10100 .
b10100 E
b10100 A
1,
#324000
0,
#325000
b10010 #
b10010 /
b1 9
b111 :
b1111 5
b1010 3
b10001 D
b1010 C
b10000 B
1)
#327000
b1111 8
b10101 K
b101 6
b110 4
b10101 '
b10101 .
b10101 E
b10101 A
1,
#330000
0,
#333000
b10110 L
b100 6
b111 4
b1111 7
b10110 '
b10110 .
b10110 E
b10110 A
1,
#336000
0,
#338000
0)
#339000
b10111 M
b1100 6
b1000 4
b10111 '
b10111 .
b10111 E
b10111 A
1,
#342000
0,
#345000
b11000 F
b1101 6
b1001 4
b11000 '
b11000 .
b11000 E
b11000 A
1,
#348000
0,
#351000
b10011 #
b10011 /
b11001 G
b1111 6
b1010 4
b1110 5
b1011 3
b111 9
b1101 :
b11001 '
b11001 .
b11001 E
b11001 A
b10010 D
b1011 C
b10001 B
1,
1)
#354000
0,
#357000
b11010 H
b1110 6
b1011 4
b1110 8
b11010 '
b11010 .
b11010 E
b11010 A
1,
#360000
0,
#363000
b1110 7
b11011 I
b11011 #
b11011 /
b1010 6
b1100 4
b11011 '
b11011 .
b11011 E
b11011 A
1,
#364000
0)
#366000
0,
#369000
b11100 J
b1011 6
b1101 4
b11100 '
b11100 .
b11100 E
b11100 A
1,
#372000
0,
#375000
b11101 K
b1001 6
b1110 4
b11101 '
b11101 .
b11101 E
b11101 A
1,
#377000
b11100 #
b11100 /
b1101 9
b1001 :
b1010 5
b1100 3
b11011 D
b1100 C
b10010 B
1)
#378000
0,
#381000
b11110 L
b1000 6
b1111 4
b1010 8
b11110 '
b11110 .
b11110 E
b11110 A
1,
#384000
0,
#387000
b1010 7
b11111 M
b0 4
b11111 '
b11111 .
b11111 E
b11111 A
1,
#390000
0,
0)
#393000
b11111 F
b1 6
b1 4
b100000 A
1,
#396000
0,
#399000
b11111 G
b11 6
b10 4
1,
#402000
0,
#403000
b11101 #
b11101 /
b1011 5
b1101 3
b1001 9
b11 :
b11100 D
b1101 C
b11011 B
1)
#405000
b11111 H
b10 6
b11 4
b1011 8
1,
#408000
0,
#411000
b1011 7
b11111 I
b110 6
b100 4
1,
#414000
0,
#416000
0)
#417000
1!
b11111 J
b111 6
b101 4
1,
#420000
0,
#423000
1,
#426000
0,
#429000
b11110 #
b11110 /
b11 9
b111 :
0"
b1001 5
b1110 3
b11101 D
b1110 C
b11100 B
1,
1)
#432000
0,
#435000
b1001 8
1,
#438000
0,
#441000
0!
b1001 7
1,
#442000
0)
#444000
0,
#447000
1!
b11111 K
b101 6
b110 4
1,
#450000
0,
#453000
1,
#455000
b11111 #
b11111 /
b1000 5
b1111 3
b111 9
b101 :
b11110 D
b1111 C
b11101 B
1)
#456000
0,
#459000
b1000 8
1,
#462000
0,
#465000
0!
b1000 7
1,
#468000
0,
0)
#471000
1!
b11111 L
b100 6
b111 4
1,
#474000
0,
#477000
1,
#480000
0,
#481000
b101 9
b100 :
b0 3
b11111 D
b10000 C
b11110 B
1)
#483000
1,
#486000
0,
#489000
1,
#492000
0,
#494000
0)
#495000
1,
#498000
0,
#501000
1,
#504000
0,
#507000
b1 5
b1 3
b100 9
b10001 C
b11111 B
1,
1)
#510000
0,
#513000
b1 8
1,
#516000
0,
#519000
0!
b1 7
1,
#520000
0)
#522000
0,
#525000
b11111 M
b1100 6
b1000 4
1,
#528000
0,
#531000
1!
b11111 F
b1101 6
b1001 4
1,
#533000
b1101 :
b11 5
b10 3
b10010 C
1)
#534000
0,
#537000
b11 8
1,
#540000
0,
#543000
0!
b11 7
1,
#546000
0,
0)
#549000
1!
b11111 G
b1111 6
b1010 4
1,
#552000
0,
#555000
1,
#558000
0,
#559000
b10 5
b11 3
b1101 9
b1111 :
b10011 C
1)
#561000
b10 8
1,
#564000
0,
#567000
0!
b10 7
1,
#570000
0,
#572000
0)
#573000
1!
b11111 H
b1110 6
b1011 4
1,
#576000
0,
#579000
1,
#582000
0,
#585000
b1111 9
b1110 :
b110 5
b100 3
b10100 C
1,
1)
#588000
0,
#591000
b110 8
1,
#594000
0,
#597000
0!
b110 7
1,
#598000
0)
#600000
0,
#603000
1!
b11111 I
b1010 6
b1100 4
1,
#606000
0,
#609000
1,
#611000
b111 5
b101 3
b1110 9
b1010 :
b10101 C
1)
#612000
0,
#615000
b111 8
1,
#618000
0,
#621000
0!
b111 7
1,
#624000
0,
0)
#627000
1!
b11111 J
b1011 6
b1101 4
1,
#630000
0,
#633000
1,
#636000
0,
#637000
b1010 9
b1011 :
b101 5
b110 3
b10110 C
1)
#639000
b101 8
1,
#642000
0,
#645000
0!
b101 7
1,
#648000
0,
#650000
0)
#651000
1!
b11111 K
b1001 6
b1110 4
1,
#654000
0,
#657000
1,
#660000
0,
#663000
b100 5
b111 3
b1011 9
b1001 :
b10111 C
1,
1)
#666000
0,
#669000
b100 8
1,
#672000
0,
#675000
0!
b100 7
1,
#676000
0)
#678000
0,
#681000
1!
b11111 L
b1000 6
b1111 4
1,
#684000
0,
#687000
1,
#689000
b1001 9
b1000 :
b1100 5
b1000 3
b11000 C
1)
#690000
0,
#693000
b1100 8
1,
#696000
0,
#699000
0!
b1100 7
1,
#702000
0,
0)
#705000
b11111 M
b0 4
1,
#708000
0,
#711000
b11111 F
b1 6
b1 4
1,
#714000
0,
#715000
b1101 5
b1001 3
b1000 9
b1 :
b11001 C
1)
#717000
b11111 G
b11 6
b10 4
b1101 8
1,
#720000
0,
#723000
b1101 7
b11111 H
b10 6
b11 4
1,
#726000
0,
#728000
0)
#729000
b11111 I
b110 6
b100 4
1,
#732000
0,
#735000
b11111 J
b111 6
b101 4
1,
#738000
0,
#741000
b11111 K
b101 6
b110 4
b1 9
b111 :
b1111 5
b1010 3
b11010 C
1,
1)
#744000
0,
#747000
b1111 8
b11111 L
b100 6
b111 4
1,
#750000
0,
#753000
b11111 M
b1100 6
b1000 4
b1111 7
1,
#754000
0)
#756000
0,
#759000
b11111 F
b1101 6
b1001 4
1,
#762000
0,
#765000
b11111 G
b1111 6
b1010 4
1,
#767000
b1110 5
b1011 3
b111 9
b1111 :
b11011 C
1)
#768000
0,
#771000
b1110 8
b11111 H
b1110 6
b1011 4
1,
#774000
0,
#777000
b11111 I
b1010 6
b1100 4
b1110 7
1,
#780000
0,
0)
#783000
b11111 J
b1011 6
b1101 4
1,
#786000
0,
#789000
b11111 K
b1001 6
b1110 4
1,
#792000
0,
#793000
b1111 9
b1001 :
b1010 5
b1100 3
b11100 C
1)
#795000
b1010 8
b11111 L
b1000 6
b1111 4
1,
#798000
0,
#801000
b11111 M
b0 4
b1010 7
1,
#804000
0,
#806000
0)
#807000
b11111 F
b1 6
b1 4
1,
#810000
0,
#813000
b11111 G
b11 6
b10 4
1,
#816000
0,
#819000
b11111 H
b10 6
b11 4
b1011 5
b1101 3
b1001 9
b11 :
b11101 C
1,
1)
#822000
0,
#825000
1!
b11111 I
b110 6
b100 4
b1011 8
1,
#828000
0,
#831000
0!
b1011 7
1,
#832000
0)
#834000
0,
#837000
1!
b11111 J
b111 6
b101 4
1,
#840000
0,
#843000
1,
#845000
b11 9
b111 :
0"
b1001 5
b1110 3
b11110 C
1)
#846000
0,
#849000
b1001 8
1,
#852000
0,
#855000
0!
b1001 7
1,
#858000
0,
0)
#861000
1!
b11111 K
b101 6
b110 4
1,
#864000
0,
#867000
1,
#870000
0,
#871000
b1000 5
b1111 3
b111 9
b101 :
b11111 C
1)
#873000
b1000 8
1,
#876000
0,
#879000
0!
b1000 7
1,
#882000
0,
#884000
0)
#885000
1!
b11111 L
b100 6
b111 4
1,
#888000
0,
#891000
1,
#894000
0,
#897000
b101 9
b100 :
b0 3
b100000 @
b11111 =
b100000 C
1,
1)
