async_fifo/async_fifo.sv
// Simple FWFT async fifo
// Restricted to depths of powers of 2

// FWFT behavior: oldest value already sitting on dout
// On first instance of ren && rclk, second-oldest value gets clocked out

module async_fifo #(
  parameter WIDTH = 16,
  parameter DEPTH = 4
)(
  input logic rclk, // read clock
  input logic wclk, // write clock
  input logic r_rst, // read domain reset
  input logic w_rst, // write domain reset
  input logic ren, // active low read enable
  input logic wen, // active low write enable
  input logic [WIDTH - 1:0] din, // data to write to fifo
  output logic [WIDTH - 1:0] dout, // data coming out of fifo
  output logic empty, // active high fifo empty flag
  output logic full // active high fifo full flag
);

  localparam POINTER_WIDTH = $clog2(DEPTH);

  logic [WIDTH - 1:0] fifo [DEPTH - 1:0]; // FIFO memory

  // intermediary signals
  // declared as POINTER_WIDTH in size because grey code requires extra MSB
  logic [POINTER_WIDTH:0] b_wptr; // binary write pointer
  logic [POINTER_WIDTH:0] b_rptr; // binary read pointer

  logic [POINTER_WIDTH:0] g_wptr; // gray code write pointer
  logic [POINTER_WIDTH:0] g_rptr; // gray code read pointer

  logic [POINTER_WIDTH:0] sync_g_wptr; // synchronized gray code write pointer
  logic [POINTER_WIDTH:0] sync_g_rptr; // synchronized gray code read pointer

  logic [POINTER_WIDTH:0] sync_g_wptr_inter; // intermediary signal in 2FF (Danger Zone!)
  logic [POINTER_WIDTH:0] sync_g_rptr_inter; // intermediary signal in 2FF (Danger Zone!)

  // empty flag asserted when synchronized write pointer equals read pointer
  assign empty = (sync_g_wptr == g_rptr);

  // full flag asserted when top two MSB of write pointer is the inverse of the top two MSB of read pointer
  // and if the rest of both are the same
  assign full = (sync_g_rptr[POINTER_WIDTH:POINTER_WIDTH-1] == ~g_wptr[POINTER_WIDTH:POINTER_WIDTH-1]) && (sync_g_rptr[POINTER_WIDTH-2:0] == g_wptr[POINTER_WIDTH-2:0]);

  // write pointer handler
  always_ff @(posedge wclk, negedge w_rst) begin
    if (~w_rst) begin
      b_wptr <= 0;
      g_wptr <= 0;

      // TODO: move this to synchronized reset block later
      for (int i = 0; i < DEPTH; i++) begin
        fifo[i] <= 0;
      end
    end else begin
      if (~wen && ~full) begin // if valid write condition
        // truncate write pointer to proper bit width
        b_wptr <= b_wptr + 1;
        g_wptr <= (b_wptr + 1) ^ ((b_wptr + 1) >> 1); // added 1 to b_wptr to account for non-blocking assignment
        fifo[b_wptr[POINTER_WIDTH - 1:0]] <= din;
      end
    end
  end

  // assign dout combinationally for FWFT behavior
  assign dout = fifo[b_rptr[POINTER_WIDTH - 1:0]];

  // read pointer handler
  always_ff @(posedge rclk, negedge r_rst) begin
    if (~r_rst) begin
      b_rptr <= 0;
      g_rptr <= 0;
    end else begin
      if (~ren && ~empty) begin // if valid read condition
        b_rptr <= b_rptr + 1;
        g_rptr <= (b_rptr + 1) ^ ((b_rptr + 1) >> 1);
      end
    end
  end

  // 2FF sync for rptr
  always_ff @(posedge wclk, negedge w_rst) begin
    if (~w_rst) begin
      sync_g_rptr_inter <= 0;
      sync_g_rptr <= 0;
    end else begin
      sync_g_rptr_inter <= g_rptr;
      sync_g_rptr <= sync_g_rptr_inter;
    end
  end

  // 2FF sync for wptr
  always_ff @(posedge rclk, negedge r_rst) begin
    if (~r_rst) begin
      sync_g_wptr_inter <= 0;
      sync_g_wptr <= 0;
    end else begin
      sync_g_wptr_inter <= g_wptr;
      sync_g_wptr <= sync_g_wptr_inter;
    end
  end

endmodule

async_fifo/tb_async_fifo.sv
// Testbench for async fifo
// Tests async FWFT behavior
// Depth restricted to powers of 2

`timescale 1ns/1ps

module tb_async_fifo;

  parameter WIDTH = 32;
  parameter DEPTH = 8;
  parameter TEST_LEN = 4096;

  // 1. Declare local signals to connect to the Design Under Test (DUT)
  logic rclk; // read clock
  logic wclk; // write clock
  logic r_rst;
  logic w_rst;
  logic ren; // active low read enable
  logic wen; // active low write enable
  logic [WIDTH - 1:0] din; // data to write to fifo
  logic [WIDTH - 1:0] dout; // data coming out of fifo
  logic empty; // active high fifo empty flag
  logic full; // active high fifo full flag

  async_fifo #(WIDTH, DEPTH) dut (.*);

  // 3. Clock Generation
  // Generate two separate clocks for write and read
  initial begin
    wclk = 0;
    forever #7ns wclk = ~wclk;
  end

  initial begin
    rclk = 0;
    forever #13ns rclk = ~rclk;
  end

  // write driver
  // checks if fifo not full and writes to it
  task write_fifo(input logic [WIDTH-1:0] test_din);
    if (~full) begin // if not full, write
      wen = 0;
      din = test_din;
      @(posedge wclk);
      $display("[%dns] Wrote %d to FIFO!", $time, test_din);
    end else begin // if full, wait
      wen = 1;
      @(posedge wclk);
      $display("[%dns] Tried to write %d, but FIFO was full!", $time, test_din);
    end
  endtask

  // read driver
  // checks if fifo not empty and reads from it
  task read_fifo(output logic [WIDTH-1:0] test_dout);
    wait (!empty);
    // if (~empty) begin // if not empty, read
      ren = 0;
      @(posedge rclk);
      test_dout = dout;
      $display("[%dns] Read %D from FIFO!", $time, test_dout);
    // end else begin // if empty, wait
    //   ren = 1;
    //   @(posedge rclk);
    //   $display("[%dns] Tried to read %d, but FIFO was empty!", $time, test_dout);
    // end
  endtask

// 4. Stimulus Generation
  initial begin
    logic [WIDTH-1:0] test_data;
    logic [WIDTH-1:0] captured_data;

    logic [WIDTH-1:0] bs_input [TEST_LEN]; // TEST_LEN-long array of input bitstreams
    logic [WIDTH-1:0] bs_output [TEST_LEN]; // FIFO output
    int errors = 0;
    
    int random_w_delay;
    int random_r_delay;

    // initialize input bitstreams
    for (int i=0; i<TEST_LEN; i++) begin
      // bs_input[i] = 32'd100 + i;
      bs_input[i] = $urandom();
    end

    $dumpfile("dump.vcd");
    $dumpvars(0, tb_async_fifo);
    for (int i = 0; i < DEPTH; i = i + 1) begin
      $dumpvars(0, tb_async_fifo.dut.fifo[i]);
    end

    // Initialize inputs
    r_rst = 0;
    w_rst = 0;
    ren   = 1;
    wen   = 1;
    din   = 0;

    // Wait for slower read clock
    repeat(3) @(posedge rclk);
    repeat(3) @(posedge wclk);
    r_rst = 1;
    w_rst = 1;
    $display("--- Starting async FIFO Tests ---");

    test_data = 32'd100;

    // for (int i=0; i<TEST_LEN; i++) begin
    //   write_fifo(bs_input[i]);
    // end

    fork
      // Thread 1: Continuous Write Loop
      begin
        int w_idx = 0;
        while(w_idx < TEST_LEN) begin
          write_fifo(bs_input[w_idx]);
          if (~full) begin
            w_idx = w_idx + 1;
          end
        end
        $display("Write thread done!");
      end

      // Thread 2: Continuous Read Loop
      begin
        int r_idx = 0;
        logic [WIDTH-1:0] read_data;
        while(r_idx < TEST_LEN) begin
          read_fifo(read_data);
          bs_output[r_idx] = read_data;
          if (~empty) begin
            r_idx = r_idx + 1;
          end
        end
      end
    join

    // 5. Post-test Verification/Self-Checking
    $display("--- Analyzing Results ---");
    for (int i = 0; i < TEST_LEN; i++) begin
      if (bs_input[i] !== bs_output[i]) begin
        $display("ERROR at index %0d: Expected %d, Got %d", i, bs_input[i], bs_output[i]);
        errors++;
      end
    end

    if (errors == 0) begin
      $display("SUCCESS: All TEST_LEN bitstream elements matched perfectly!");
    end else begin
      $display("FAILURE: %0d mismatches detected.", errors);
    end

    $display("--- Tests Complete! ---");
    $finish;
  end

endmodule

async_fifo/dump.vcd
$date
	Sat Jun  6 22:31:21 2026
$end
$version
	Icarus Verilog
$end
$timescale
	1ps
$end
$scope module tb_async_fifo $end
$var wire 1 ! full $end
$var wire 1 " empty $end
$var wire 32 # dout [31:0] $end
$var parameter 32 $ DEPTH $end
$var parameter 32 % TEST_LEN $end
$var parameter 32 & WIDTH $end
$var reg 32 ' din [31:0] $end
$var reg 1 ( r_rst $end
$var reg 1 ) rclk $end
$var reg 1 * ren $end
$var reg 1 + w_rst $end
$var reg 1 , wclk $end
$var reg 1 - wen $end
$scope module dut $end
$var wire 32 . din [31:0] $end
$var wire 32 / dout [31:0] $end
$var wire 1 ! full $end
$var wire 1 ( r_rst $end
$var wire 1 ) rclk $end
$var wire 1 * ren $end
$var wire 1 + w_rst $end
$var wire 1 , wclk $end
$var wire 1 - wen $end
$var wire 1 " empty $end
$var parameter 32 0 DEPTH $end
$var parameter 32 1 POINTER_WIDTH $end
$var parameter 32 2 WIDTH $end
$var reg 4 3 b_rptr [3:0] $end
$var reg 4 4 b_wptr [3:0] $end
$var reg 4 5 g_rptr [3:0] $end
$var reg 4 6 g_wptr [3:0] $end
$var reg 4 7 sync_g_rptr [3:0] $end
$var reg 4 8 sync_g_rptr_inter [3:0] $end
$var reg 4 9 sync_g_wptr [3:0] $end
$var reg 4 : sync_g_wptr_inter [3:0] $end
$upscope $end
$scope begin $unm_blk_19 $end
$var reg 32 ; test_data [31:0] $end
$var integer 32 < errors [31:0] $end
$scope begin $ivl_for_loop0 $end
$var integer 32 = i [31:0] $end
$upscope $end
$scope begin $ivl_for_loop1 $end
$var integer 32 > i [31:0] $end
$upscope $end
$scope begin $ivl_for_loop2 $end
$var integer 32 ? i [31:0] $end
$upscope $end
$scope begin $unm_blk_23 $end
$var integer 32 @ w_idx [31:0] $end
$upscope $end
$scope begin $unm_blk_26 $end
$var reg 32 A read_data [31:0] $end
$var integer 32 B r_idx [31:0] $end
$upscope $end
$upscope $end
$scope task read_fifo $end
$var reg 32 C test_dout [31:0] $end
$upscope $end
$scope task write_fifo $end
$var reg 32 D test_din [31:0] $end
$upscope $end
$upscope $end
$scope module tb_async_fifo $end
$scope module dut $end
$var reg 32 E \fifo[0] [31:0] $end
$upscope $end
$upscope $end
$scope module tb_async_fifo $end
$scope module dut $end
$var reg 32 F \fifo[1] [31:0] $end
$upscope $end
$upscope $end
$scope module tb_async_fifo $end
$scope module dut $end
$var reg 32 G \fifo[2] [31:0] $end
$upscope $end
$upscope $end
$scope module tb_async_fifo $end
$scope module dut $end
$var reg 32 H \fifo[3] [31:0] $end
$upscope $end
$upscope $end
$scope module tb_async_fifo $end
$scope module dut $end
$var reg 32 I \fifo[4] [31:0] $end
$upscope $end
$upscope $end
$scope module tb_async_fifo $end
$scope module dut $end
$var reg 32 J \fifo[5] [31:0] $end
$upscope $end
$upscope $end
$scope module tb_async_fifo $end
$scope module dut $end
$var reg 32 K \fifo[6] [31:0] $end
$upscope $end
$upscope $end
$scope module tb_async_fifo $end
$scope module dut $end
$var reg 32 L \fifo[7] [31:0] $end
$upscope $end
$upscope $end
$enddefinitions $end
$comment Show the parameter values. $end
$dumpall
b100000 2
b11 1
b1000 0
b100000 &
b1000000000000 %
b1000 $
$end
#0
$dumpvars
bx L
bx K
bx J
bx I
bx H
bx G
bx F
bx E
bx D
bx C
b0 B
bx A
b0 @
b0 ?
b1000 >
b1000000000000 =
b0 <
bx ;
b0 :
b0 9
b0 8
b0 7
b0 6
b0 5
b0 4
b0 3
bx /
b0 .
1-
0,
0+
1*
0)
0(
b0 '
bx #
1"
0!
$end
#7000
1,
#13000
1)
#14000
0,
#21000
1,
#26000
0)
#28000
0,
#35000
1,
#39000
1)
#42000
0,
#49000
1,
#52000
0)
#56000
0,
#63000
1,
#65000
1)
#70000
0,
#77000
1,
#78000
0)
#84000
0,
#91000
1,
1)
#98000
0,
#104000
0)
#105000
b10010010000101010011010100100100 E
b10010010000101010011010100100100 #
b10010010000101010011010100100100 /
b1 6
b1 4
b10010010000101010011010100100100 '
b10010010000101010011010100100100 .
0-
b10010010000101010011010100100100 D
b1100100 ;
1+
1(
1,
#112000
0,
#117000
b1 :
1)
#119000
b1000000100010010101111010000001 F
b11 6
b10 4
b1000000100010010101111010000001 '
b1000000100010010101111010000001 .
b1000000100010010101111010000001 D
b1 @
1,
#126000
0,
#130000
0)
#133000
b100100001001101011000001001 G
b10 6
b11 4
b100100001001101011000001001 '
b100100001001101011000001001 .
b100100001001101011000001001 D
b10 @
1,
#140000
0,
#143000
0*
0"
b1 9
b10 :
1)
#147000
b110001111100000101011001100011 H
b110 6
b100 4
b110001111100000101011001100011 '
b110001111100000101011001100011 .
b110001111100000101011001100011 D
b11 @
1,
#154000
0,
#156000
0)
#161000
b10000110101110010111101100001101 I
b111 6
b101 4
b10000110101110010111101100001101 '
b10000110101110010111101100001101 .
b10000110101110010111101100001101 D
b100 @
1,
#168000
0,
#169000
b1000000100010010101111010000001 #
b1000000100010010101111010000001 /
b10 9
b111 :
0"
b1 5
b1 3
b1 B
b10010010000101010011010100100100 A
b10010010000101010011010100100100 C
1)
#175000
b1 8
b11000110110111111001100110001101 J
b101 6
b110 4
b11000110110111111001100110001101 '
b11000110110111111001100110001101 .
b11000110110111111001100110001101 D
b101 @
1,
#182000
0,
0)
#189000
b110010110000101000010001100101 K
b100 6
b111 4
b1 7
b110010110000101000010001100101 '
b110010110000101000010001100101 .
b110010110000101000010001100101 D
b110 @
1,
#195000
b100100001001101011000001001 #
b100100001001101011000001001 /
b11 5
b10 3
b111 9
b100 :
b10 B
b1000000100010010101111010000001 A
b1000000100010010101111010000001 C
1)
#196000
0,
#203000
b11 8
b1001001101110101001000010010 L
b1100 6
b1000 4
b1001001101110101001000010010 '
b1001001101110101001000010010 .
b1001001101110101001000010010 D
b111 @
1,
#208000
0)
#210000
0,
#217000
b10000000111100111110001100000001 E
b1101 6
b1001 4
b11 7
b10000000111100111110001100000001 '
b10000000111100111110001100000001 .
b10000000111100111110001100000001 D
b1000 @
1,
#221000
b110001111100000101011001100011 #
b110001111100000101011001100011 /
b100 9
b1101 :
b10 5
b11 3
b11 B
b100100001001101011000001001 A
b100100001001101011000001001 C
1)
#224000
0,
#231000
1!
b10 8
b10000110110101111100110100001101 F
b1111 6
b1010 4
b10000110110101111100110100001101 '
b10000110110101111100110100001101 .
b10000110110101111100110100001101 D
b1001 @
1,
#234000
0)
#238000
0,
#245000
0!
b10 7
1-
1,
#247000
b10000110101110010111101100001101 #
b10000110101110010111101100001101 /
b110 5
b100 3
b1101 9
b1111 :
b100 B
b110001111100000101011001100011 A
b110001111100000101011001100011 C
1)
#252000
0,
#259000
1!
b110 8
b10111011001000111111000101110110 G
b1110 6
b1011 4
b10111011001000111111000101110110 '
b10111011001000111111000101110110 .
0-
b10111011001000111111000101110110 D
b1010 @
1,
#260000
0)
#266000
0,
#273000
0!
b11000110110111111001100110001101 #
b11000110110111111001100110001101 /
b110 7
b1111 9
b1110 :
b111 5
b101 3
1-
b101 B
b10000110101110010111101100001101 A
b10000110101110010111101100001101 C
1,
1)
#280000
0,
#286000
0)
#287000
1!
b111 8
b10011110100011011100110100111101 H
b1010 6
b1100 4
b10011110100011011100110100111101 '
b10011110100011011100110100111101 .
0-
b10011110100011011100110100111101 D
b1011 @
1,
#294000
0,
#299000
b110010110000101000010001100101 #
b110010110000101000010001100101 /
b101 5
b110 3
b1110 9
b1010 :
b110 B
b11000110110111111001100110001101 A
b11000110110111111001100110001101 C
1)
#301000
0!
b111 7
b101 8
1-
1,
#308000
0,
#312000
0)
#315000
b101 7
b11110110110101000101011111101101 I
b1011 6
b1101 4
b11110110110101000101011111101101 '
b11110110110101000101011111101101 .
0-
b11110110110101000101011111101101 D
b1100 @
1,
#322000
0,
#325000
b1001001101110101001000010010 #
b1001001101110101001000010010 /
b1010 9
b1011 :
b100 5
b111 3
b111 B
b110010110000101000010001100101 A
b110010110000101000010001100101 C
1)
#329000
1!
b11000110001011011111011110001100 J
b1001 6
b1110 4
b100 8
b11000110001011011111011110001100 '
b11000110001011011111011110001100 .
b11000110001011011111011110001100 D
b1101 @
1,
#336000
0,
#338000
0)
#343000
0!
b100 7
1-
1,
#350000
0,
#351000
b10000000111100111110001100000001 #
b10000000111100111110001100000001 /
b1100 5
b1000 3
b1011 9
b1001 :
b1000 B
b1001001101110101001000010010 A
b1001001101110101001000010010 C
1)
#357000
1!
b11111100111111011110100111111001 K
b1000 6
b1111 4
b1100 8
b11111100111111011110100111111001 '
b11111100111111011110100111111001 .
0-
b11111100111111011110100111111001 D
b1110 @
1,
#364000
0,
0)
#371000
0!
b1100 7
1-
1,
#377000
b10000110110101111100110100001101 #
b10000110110101111100110100001101 /
b1001 9
b1000 :
b1101 5
b1001 3
b1001 B
b10000000111100111110001100000001 A
b10000000111100111110001100000001 C
1)
#378000
0,
#385000
b1100011001101110010010011000110 L
b0 4
b1101 8
b1100011001101110010010011000110 '
b1100011001101110010010011000110 .
0-
b1100011001101110010010011000110 D
b1111 @
1,
#390000
0)
#392000
0,
#399000
1!
b1101 7
b1100010111101111000010011000101 E
b1 6
b1 4
b1100010111101111000010011000101 '
b1100010111101111000010011000101 .
b1100010111101111000010011000101 D
b10000 @
1,
#403000
b10111011001000111111000101110110 #
b10111011001000111111000101110110 /
b1111 5
b1010 3
b1000 9
b1 :
b1010 B
b10000110110101111100110100001101 A
b10000110110101111100110100001101 C
1)
#406000
0,
#413000
b1111 8
1-
1,
#416000
0)
#420000
0,
#427000
0!
b1111 7
1,
#429000
b10011110100011011100110100111101 #
b10011110100011011100110100111101 /
b1 9
b1110 5
b1011 3
b1011 B
b10111011001000111111000101110110 A
b10111011001000111111000101110110 C
1)
#434000
0,
#441000
1!
b1010101000100111101001010101010 F
b11 6
b10 4
b1110 8
b1010101000100111101001010101010 '
b1010101000100111101001010101010 .
0-
b1010101000100111101001010101010 D
b10001 @
1,
#442000
0)
#448000
0,
#455000
0!
b11110110110101000101011111101101 #
b11110110110101000101011111101101 /
b1110 7
b1010 5
b1100 3
b11 :
1-
b1100 B
b10011110100011011100110100111101 A
b10011110100011011100110100111101 C
1,
1)
#462000
0,
#468000
0)
#469000
1!
b11110010101011111111011111100101 G
b10 6
b11 4
b1010 8
b11110010101011111111011111100101 '
b11110010101011111111011111100101 .
0-
b11110010101011111111011111100101 D
b10010 @
1,
#476000
0,
#481000
b11000110001011011111011110001100 #
b11000110001011011111011110001100 /
b11 9
b10 :
b1011 5
b1101 3
b1101 B
b11110110110101000101011111101101 A
b11110110110101000101011111101101 C
1)
#483000
0!
b1010 7
b1011 8
1-
1,
#490000
0,
#494000
0)
#497000
b111011110100100111001001110111 H
b110 6
b100 4
b1011 7
b111011110100100111001001110111 '
b111011110100100111001001110111 .
0-
b111011110100100111001001110111 D
b10011 @
1,
#504000
0,
#507000
b11111100111111011110100111111001 #
b11111100111111011110100111111001 /
b1001 5
b1110 3
b10 9
b110 :
b1110 B
b11000110001011011111011110001100 A
b11000110001011011111011110001100 C
1)
#511000
1!
b1001 8
b1001001100101101011000010010 I
b111 6
b101 4
b1001001100101101011000010010 '
b1001001100101101011000010010 .
b1001001100101101011000010010 D
b10100 @
1,
#518000
0,
#520000
0)
#525000
0!
b1001 7
1-
1,
#532000
0,
#533000
b1100011001101110010010011000110 #
b1100011001101110010010011000110 /
b110 9
b111 :
b1000 5
b1111 3
b1111 B
b11111100111111011110100111111001 A
b11111100111111011110100111111001 C
1)
#539000
1!
b1000 8
b11000111111011001101101110001111 J
b101 6
b110 4
b11000111111011001101101110001111 '
b11000111111011001101101110001111 .
0-
b11000111111011001101101110001111 D
b10101 @
1,
#546000
0,
0)
#553000
0!
b1000 7
1-
1,
#559000
b1100010111101111000010011000101 #
b1100010111101111000010011000101 /
b0 3
b111 9
b101 :
b10000 B
b1100011001101110010010011000110 A
b1100011001101110010010011000110 C
1)
#560000
0,
#567000
1!
b11111001001100000110100111110010 K
b100 6
b111 4
b11111001001100000110100111110010 '
b11111001001100000110100111110010 .
0-
b11111001001100000110100111110010 D
b10110 @
1,
#572000
0)
#574000
0,
#581000
1-
1,
#585000
b1010101000100111101001010101010 #
b1010101000100111101001010101010 /
b101 9
b100 :
b1 5
b1 3
b10001 B
b1100010111101111000010011000101 A
b1100010111101111000010011000101 C
1)
#588000
0,
#595000
b1 8
1,
#598000
0)
#602000
0,
#609000
0!
b1 7
1,
#611000
b11110010101011111111011111100101 #
b11110010101011111111011111100101 /
b11 5
b10 3
b100 9
b10010 B
b1010101000100111101001010101010 A
b1010101000100111101001010101010 C
1)
#616000
0,
#623000
b11 8
b1100111011101101001011011001110 L
b1100 6
b1000 4
b1100111011101101001011011001110 '
b1100111011101101001011011001110 .
0-
b1100111011101101001011011001110 D
b10111 @
1,
#624000
0)
#630000
0,
#637000
b111011110100100111001001110111 #
b111011110100100111001001110111 /
b1110100000000000111101011101000 E
b1101 6
b1001 4
b11 7
b1100 :
b10 5
b11 3
b1110100000000000111101011101000 '
b1110100000000000111101011101000 .
b1110100000000000111101011101000 D
b11000 @
b10011 B
b11110010101011111111011111100101 A
b11110010101011111111011111100101 C
1,
1)
#644000
0,
#650000
0)
#651000
1!
b10 8
b1100010110010100100111011000101 F
b1111 6
b1010 4
b1100010110010100100111011000101 '
b1100010110010100100111011000101 .
b1100010110010100100111011000101 D
b11001 @
1,
#658000
0,
#663000
b1001001100101101011000010010 #
b1001001100101101011000010010 /
b110 5
b100 3
b1100 9
b1111 :
b10100 B
b111011110100100111001001110111 A
b111011110100100111001001110111 C
1)
#665000
0!
b10 7
b110 8
1-
1,
#672000
0,
#676000
0)
#679000
b110 7
b10101110010110000100100101011100 G
b1110 6
b1011 4
b10101110010110000100100101011100 '
b10101110010110000100100101011100 .
0-
b10101110010110000100100101011100 D
b11010 @
1,
#686000
0,
#689000
b11000111111011001101101110001111 #
b11000111111011001101101110001111 /
b1111 9
b1110 :
b111 5
b101 3
b10101 B
b1001001100101101011000010010 A
b1001001100101101011000010010 C
1)
#693000
1!
b1011110100011100010100010111101 H
b1010 6
b1100 4
b111 8
b1011110100011100010100010111101 '
b1011110100011100010100010111101 .
b1011110100011100010100010111101 D
b11011 @
1,
#700000
0,
#702000
0)
#707000
0!
b111 7
1-
1,
#714000
0,
#715000
b11111001001100000110100111110010 #
b11111001001100000110100111110010 /
b101 5
b110 3
b1110 9
b1010 :
b10110 B
b11000111111011001101101110001111 A
b11000111111011001101101110001111 C
1)
#721000
1!
b10110101010110101100000101101 I
b1011 6
b1101 4
b101 8
b10110101010110101100000101101 '
b10110101010110101100000101101 .
0-
b10110101010110101100000101101 D
b11100 @
1,
#728000
0,
0)
#735000
0!
b101 7
1-
1,
#741000
b1100111011101101001011011001110 #
b1100111011101101001011011001110 /
b1010 9
b1011 :
b100 5
b111 3
b10111 B
b11111001001100000110100111110010 A
b11111001001100000110100111110010 C
1)
#742000
0,
#749000
1!
b110010101001110010011001100101 J
b1001 6
b1110 4
b100 8
b110010101001110010011001100101 '
b110010101001110010011001100101 .
0-
b110010101001110010011001100101 D
b11101 @
1,
#754000
0)
#756000
0,
#763000
0!
b100 7
1-
1,
#767000
b1110100000000000111101011101000 #
b1110100000000000111101011101000 /
b1100 5
b1000 3
b1011 9
b1001 :
b11000 B
b1100111011101101001011011001110 A
b1100111011101101001011011001110 C
1)
#770000
0,
#777000
1!
b110001111011110110001001100011 K
b1000 6
b1111 4
b1100 8
b110001111011110110001001100011 '
b110001111011110110001001100011 .
0-
b110001111011110110001001100011 D
b11110 @
1,
#780000
0)
#784000
0,
#791000
0!
b1100 7
1-
1,
#793000
b1100010110010100100111011000101 #
b1100010110010100100111011000101 /
b1001 9
b1000 :
b1101 5
b1001 3
b11001 B
b1110100000000000111101011101000 A
b1110100000000000111101011101000 C
1)
#798000
0,
#805000
b10000101011100111000011100001010 L
b0 4
b1101 8
b10000101011100111000011100001010 '
b10000101011100111000011100001010 .
0-
b10000101011100111000011100001010 D
b11111 @
1,
#806000
0)
#812000
0,
#819000
1!
b10101110010110000100100101011100 #
b10101110010110000100100101011100 /
b1101 7
b1000000001110110010001010000000 E
b1 6
b1 4
b1111 5
b1010 3
b1000 9
b1000000001110110010001010000000 '
b1000000001110110010001010000000 .
b1000000001110110010001010000000 D
b100000 @
b11010 B
b1100010110010100100111011000101 A
b1100010110010100100111011000101 C
1,
1)
#826000
0,
#832000
0)
#833000
b1111 8
1-
1,
#840000
0,
#845000
b1011110100011100010100010111101 #
b1011110100011100010100010111101 /
b1 :
b1110 5
b1011 3
b11011 B
b10101110010110000100100101011100 A
b10101110010110000100100101011100 C
1)
#847000
0!
b1111 7
b1110 8
1,
#854000
0,
#858000
0)
#861000
b10010000011001000010000100100000 F
b11 6
b10 4
b1110 7
b10010000011001000010000100100000 '
b10010000011001000010000100100000 .
0-
b10010000011001000010000100100000 D
b100001 @
1,
#868000
0,
#871000
b10110101010110101100000101101 #
b10110101010110101100000101101 /
b1010 5
b1100 3
b1 9
b11 :
b11100 B
b1011110100011100010100010111101 A
b1011110100011100010100010111101 C
1)
#875000
1!
b1010 8
b11010101011110000100010110101010 G
b10 6
b11 4
b11010101011110000100010110101010 '
b11010101011110000100010110101010 .
b11010101011110000100010110101010 D
b100010 @
1,
#882000
0,
#884000
0)
#889000
0!
b1010 7
1-
1,
#896000
0,
#897000
b110010101001110010011001100101 #
b110010101001110010011001100101 /
b11 9
b10 :
b1011 5
b1101 3
b11101 B
b10110101010110101100000101101 A
b10110101010110101100000101101 C
1)
#903000
1!
b1011 8
b1001110110011001100110010011101 H
b110 6
b100 4
b1001110110011001100110010011101 '
b1001110110011001100110010011101 .
0-
b1001110110011001100110010011101 D
b100011 @
1,
#910000
0,
0)
#917000
0!
b1011 7
1-
1,
#923000
b110001111011110110001001100011 #
b110001111011110110001001100011 /
b1001 5
b1110 3
b10 9
b110 :
b11110 B
b110010101001110010011001100101 A
b110010101001110010011001100101 C
1)
#924000
0,
#931000
1!
b1001 8
b1001011001000000011111010010110 I
b111 6
b101 4
b1001011001000000011111010010110 '
b1001011001000000011111010010110 .
0-
b1001011001000000011111010010110 D
b100100 @
1,
#936000
0)
#938000
0,
#945000
0!
b1001 7
1-
1,
#949000
b10000101011100111000011100001010 #
b10000101011100111000011100001010 /
b110 9
b111 :
b1000 5
b1111 3
b11111 B
b110001111011110110001001100011 A
b110001111011110110001001100011 C
1)
#952000
0,
#959000
1!
b1000 8
b1001100000111011100000010011 J
b101 6
b110 4
b1001100000111011100000010011 '
b1001100000111011100000010011 .
0-
b1001100000111011100000010011 D
b100101 @
1,
#962000
0)
#966000
0,
#973000
0!
b1000 7
1-
1,
#975000
b1000000001110110010001010000000 #
b1000000001110110010001010000000 /
b0 3
b111 9
b101 :
b100000 B
b10000101011100111000011100001010 A
b10000101011100111000011100001010 C
1)
#980000
0,
#987000
1!
b110101111000011100000001101 K
b100 6
b111 4
b110101111000011100000001101 '
b110101111000011100000001101 .
0-
b110101111000011100000001101 D
b100110 @
1,
#988000
0)
#994000
0,
#1001000
b10010000011001000010000100100000 #
b10010000011001000010000100100000 /
b101 9
b100 :
b1 5
b1 3
1-
b100001 B
b1000000001110110010001010000000 A
b1000000001110110010001010000000 C
1,
1)
#1008000
0,
#1014000
0)
#1015000
b1 8
1,
#1022000
0,
#1027000
b11010101011110000100010110101010 #
b11010101011110000100010110101010 /
b11 5
b10 3
b100 9
b100010 B
b10010000011001000010000100100000 A
b10010000011001000010000100100000 C
1)
#1029000
0!
b1 7
b11 8
1,
#1036000
0,
#1040000
0)
#1043000
b11 7
b101001101001111101011001010011 L
b1100 6
b1000 4
b101001101001111101011001010011 '
b101001101001111101011001010011 .
0-
b101001101001111101011001010011 D
b100111 @
1,
#1050000
0,
#1053000
b1001110110011001100110010011101 #
b1001110110011001100110010011101 /
b1100 :
b10 5
b11 3
b100011 B
b11010101011110000100010110101010 A
b11010101011110000100010110101010 C
1)
#1057000
b10110101100111111101110101101011 E
b1101 6
b1001 4
b10 8
b10110101100111111101110101101011 '
b10110101100111111101110101101011 .
b10110101100111111101110101101011 D
b101000 @
1,
#1064000
0,
#1066000
0)
#1071000
b10 7
b1101010101001100010101011010101 F
b1111 6
b1010 4
b1101010101001100010101011010101 '
b1101010101001100010101011010101 .
b1101010101001100010101011010101 D
b101001 @
1,
#1078000
0,
#1079000
b1001011001000000011111010010110 #
b1001011001000000011111010010110 /
b110 5
b100 3
b1100 9
b1111 :
b100100 B
b1001110110011001100110010011101 A
b1001110110011001100110010011101 C
1)
#1085000
1!
b1000101110100101000000010 G
b1110 6
b1011 4
b110 8
b1000101110100101000000010 '
b1000101110100101000000010 .
b1000101110100101000000010 D
b101010 @
1,
#1092000
0,
0)
#1099000
0!
b110 7
1-
1,
#1105000
b1001100000111011100000010011 #
b1001100000111011100000010011 /
b1111 9
b1110 :
b111 5
b101 3
b100101 B
b1001011001000000011111010010110 A
b1001011001000000011111010010110 C
1)
#1106000
0,
#1113000
1!
b1010111010101100011111010101110 H
b1010 6
b1100 4
b111 8
b1010111010101100011111010101110 '
b1010111010101100011111010101110 .
0-
b1010111010101100011111010101110 D
b101011 @
1,
#1118000
0)
#1120000
0,
#1127000
0!
b111 7
1-
1,
#1131000
b110101111000011100000001101 #
b110101111000011100000001101 /
b101 5
b110 3
b1110 9
b1010 :
b100110 B
b1001100000111011100000010011 A
b1001100000111011100000010011 C
1)
#1134000
0,
#1141000
1!
b10001110111111111110100100011101 I
b1011 6
b1101 4
b101 8
b10001110111111111110100100011101 '
b10001110111111111110100100011101 .
0-
b10001110111111111110100100011101 D
b101100 @
1,
#1144000
0)
#1148000
0,
#1155000
0!
b101 7
1-
1,
#1157000
b101001101001111101011001010011 #
b101001101001111101011001010011 /
b1010 9
b1011 :
b100 5
b111 3
b100111 B
b110101111000011100000001101 A
b110101111000011100000001101 C
1)
#1162000
0,
#1169000
1!
b1100111110001010111001011001111 J
b1001 6
b1110 4
b100 8
b1100111110001010111001011001111 '
b1100111110001010111001011001111 .
0-
b1100111110001010111001011001111 D
b101101 @
1,
#1170000
0)
#1176000
0,
#1183000
0!
b10110101100111111101110101101011 #
b10110101100111111101110101101011 /
b100 7
b1100 5
b1000 3
b1011 9
b1001 :
1-
b101000 B
b101001101001111101011001010011 A
b101001101001111101011001010011 C
1,
1)
#1190000
0,
#1196000
0)
