async_fifo/async_fifo.sv
// Simple FWFT async fifo
// Restricted to depths of powers of 2

module async_fifo #(
  parameter WIDTH = 16,
  parameter DEPTH = 4
)(
  input logic rclk, // read clock
  input logic wclk, // write clock
  input logic n_rst,
  input logic ren, // active low read enable
  input logic wen, // active low write enable
  input logic [WIDTH - 1:0] din, // data to write to fifo
  output logic [WIDTH - 1:0] dout, // data coming out of fifo
  output logic empty, // active high fifo empty flag
  output logic full // active high fifo full flag
);

  localparam POINTER_WIDTH = $clog2(DEPTH);

  logic [WIDTH - 1:0] fifo [DEPTH - 1:0]; // FIFO memory

  // intermediary signals
  // declared as POINTER_WIDTH in size because grey code requires extra MSB
  logic [POINTER_WIDTH:0] b_wptr; // binary write pointer
  logic [POINTER_WIDTH:0] b_rptr; // binary read pointer

  logic [POINTER_WIDTH:0] g_wptr; // gray code write pointer
  logic [POINTER_WIDTH:0] g_rptr; // gray code read pointer

  logic [POINTER_WIDTH:0] sync_g_wptr; // synchronized gray code write pointer
  logic [POINTER_WIDTH:0] sync_g_rptr; // synchronized gray code read pointer

  logic [POINTER_WIDTH:0] sync_g_wptr_inter; // intermediary signal in 2FF (Danger Zone!)
  logic [POINTER_WIDTH:0] sync_g_rptr_inter; // intermediary signal in 2FF (Danger Zone!)

  // empty flag asserted when synchronized write pointer equals read pointer
  assign empty = (sync_g_wptr == g_rptr);

  // full flag asserted when top two MSB of write pointer is the inverse of the top two MSB of read pointer
  // and if the rest of both are the same
  assign full = (sync_g_rptr[POINTER_WIDTH:POINTER_WIDTH-1] == ~g_wptr[POINTER_WIDTH:POINTER_WIDTH-1]) && (sync_g_rptr[POINTER_WIDTH-2:0] == g_wptr[POINTER_WIDTH-2:0]);

  // write pointer handler
  always_ff @(posedge wclk, negedge n_rst) begin
    if (~n_rst) begin
      b_wptr <= 0;
      g_wptr <= 0;

      // TODO: move this to synchronized reset block later
      for (int i = 0; i < DEPTH; i++) begin
        fifo[i] <= 0;
      end
    end else begin
      if (~wen && ~full) begin // if valid write condition
        // truncate write pointer to proper bit width
        b_wptr <= b_wptr + 1;
        g_wptr <= (b_wptr + 1) ^ ((b_wptr + 1) >> 1); // added 1 to b_wptr to account for non-blocking assignment
        fifo[b_wptr[POINTER_WIDTH - 1:0]] <= din;
      end
    end
  end

  // assign dout combinationally for FWFT behavior
  assign dout = fifo[b_rptr[POINTER_WIDTH - 1:0]];

  // read pointer handler
  always_ff @(posedge rclk, negedge n_rst) begin
    if (~n_rst) begin
      b_rptr <= 0;
      g_rptr <= 0;
    end else begin
      if (~ren && ~empty) begin // if valid read condition
        b_rptr <= b_rptr + 1;
        g_rptr <= b_rptr + 1 ^ (b_rptr + 1 >> 1);
      end
    end
  end

  // 2FF sync for rptr
  always_ff @(posedge wclk, negedge n_rst) begin
    if (~n_rst) begin
      sync_g_rptr_inter <= 0;
      sync_g_rptr <= 0;
    end else begin
      sync_g_rptr_inter <= g_rptr;
      sync_g_rptr <= sync_g_rptr_inter;
    end
  end

  // 2FF sync for wptr
  always_ff @(posedge rclk, negedge n_rst) begin
    if (~n_rst) begin
      sync_g_wptr_inter <= 0;
      sync_g_wptr <= 0;
    end else begin
      sync_g_wptr_inter <= g_wptr;
      sync_g_wptr <= sync_g_wptr_inter;
    end
  end

endmodule

async_fifo/tb_async_fifo.sv
// Testbench for async fifo
// Tests async FWFT behavior
// Depth restricted to powers of 2

`timescale 1ns/1ps

module tb_async_fifo;

  parameter WIDTH = 32;
  parameter DEPTH = 8;

  // 1. Declare local signals to connect to the Design Under Test (DUT)
  logic rclk; // read clock
  logic wclk; // write clock
  logic n_rst;
  logic ren; // active low read enable
  logic wen; // active low write enable
  logic [WIDTH - 1:0] din; // data to write to fifo
  logic [WIDTH - 1:0] dout; // data coming out of fifo
  logic empty; // active high fifo empty flag
  logic full; // active high fifo full flag

  async_fifo #(WIDTH, DEPTH) dut (.*);

  // 3. Clock Generation
  // Generate two separate clocks for write and read
  initial begin
    wclk = 0;
    forever #10ns wclk = ~wclk;
  end

  initial begin
    rclk = 0;
    forever #5ns rclk = ~rclk;
  end

  // write driver
  // checks if fifo not full and writes to it
  task write_fifo(input logic [WIDTH-1:0] test_din);
    if (~full) begin // if not full, write
      wen = 0;
      din = test_din;
      @(posedge wclk);
    end else begin // if full, wait
      wen = 1;
      @(posedge wclk);
      $display("FIFO full!");
    end
  endtask

  // read driver
  // checks if fifo not empty and reads from it
  task read_fifo(output logic [WIDTH-1:0] test_dout);
    if (~empty) begin // if not empty, read
      ren = 0;
      @(posedge rclk);
      test_dout = dout;
    end else begin // if empty, wait
      ren = 1;
      @(posedge rclk);
      $display("FIFO empty!");
    end
  endtask

// 4. Stimulus Generation
  initial begin
    logic [WIDTH-1:0] test_data;
    logic [WIDTH-1:0] captured_data;

    int random_w_delay;
    int random_r_delay;

    $dumpfile("dump.vcd");
    $dumpvars(0, tb_async_fifo);
    for (int i = 0; i < DEPTH; i = i + 1) begin
      $dumpvars(0, tb_async_fifo.dut.fifo[i]);
    end

    // Initialize inputs
    n_rst = 0;
    ren   = 1;
    wen   = 1;
    din   = 0;

    // Wait for slower read clock
    repeat(3) @(posedge rclk);
    n_rst = 1; // Release reset
    $display("--- Starting async FIFO Tests ---");

    test_data = 32'd100;

    for (int i=0; i<DEPTH + 10; i++) begin
      write_fifo(test_data);
      $display("Wrote %h to FIFO slot %d!", test_data, i);
      if (~full) begin
        test_data++;
      end
    end

    for (int i=0; i<DEPTH + 10; i++) begin
      read_fifo(captured_data);
      $display("Read %h from FIFO slot %d!", captured_data, i);
    end

    n_rst = 0;
    repeat(3) @(posedge rclk);
    n_rst = 1;

    // Fix 2: Put loops inside the fork, and control time with join_any
    fork
      // Thread 1: Continuous Write Loop
      begin
        forever begin
          // random delay for 0 to 2 clock cycles
          // random_w_delay = $urandom_range(0, 5);
          random_w_delay = 0;
          repeat(random_w_delay) @(posedge wclk);

          write_fifo(test_data);
          // Only increment data if the write actually succeeded (FIFO wasn't full)
          if (~full) begin
            test_data++;
          end
        end
      end

      // Thread 2: Continuous Read Loop
      begin
        forever begin
          // random delay for 0 to 2 clock cycles
          random_r_delay = 0;
          // random_r_delay = $urandom_range(0, 5);
          repeat(random_r_delay) @(posedge rclk);

          read_fifo(captured_data);
          if (~empty) begin
            $display("[%0t ns] RxFIFO Read: %h", $time, captured_data);
          end
        end
      end

      // Thread 3: Simulation Timer (Runs everything for 5000 NANOSECONDS)
      #10000ns;

    join_any // Unblocks the moment the 5000ns timer finishes

    // Fix 3: Kill the infinite 'forever' loops so the simulation can exit
    disable fork; 

    $display("--- Tests Complete! ---");
    $finish;
  end

endmodule

async_fifo/dump.vcd
$date
	Sun May 31 17:26:22 2026
$end
$version
	Icarus Verilog
$end
$timescale
	1ps
$end
$scope module tb_async_fifo $end
$var wire 1 ! full $end
$var wire 1 " empty $end
$var wire 32 # dout [31:0] $end
$var parameter 32 $ DEPTH $end
$var parameter 32 % WIDTH $end
$var reg 32 & din [31:0] $end
$var reg 1 ' n_rst $end
$var reg 1 ( rclk $end
$var reg 1 ) ren $end
$var reg 1 * wclk $end
$var reg 1 + wen $end
$scope module dut $end
$var wire 32 , din [31:0] $end
$var wire 32 - dout [31:0] $end
$var wire 1 ! full $end
$var wire 1 ' n_rst $end
$var wire 1 ( rclk $end
$var wire 1 ) ren $end
$var wire 1 * wclk $end
$var wire 1 + wen $end
$var wire 1 " empty $end
$var parameter 32 . DEPTH $end
$var parameter 32 / POINTER_WIDTH $end
$var parameter 32 0 WIDTH $end
$var reg 4 1 b_rptr [3:0] $end
$var reg 4 2 b_wptr [3:0] $end
$var reg 4 3 g_rptr [3:0] $end
$var reg 4 4 g_wptr [3:0] $end
$var reg 4 5 sync_g_rptr [3:0] $end
$var reg 4 6 sync_g_rptr_inter [3:0] $end
$var reg 4 7 sync_g_wptr [3:0] $end
$var reg 4 8 sync_g_wptr_inter [3:0] $end
$scope begin $ivl_for_loop0 $end
$var integer 32 9 i [31:0] $end
$upscope $end
$upscope $end
$scope begin $unm_blk_22 $end
$var reg 32 : captured_data [31:0] $end
$var reg 32 ; test_data [31:0] $end
$var integer 32 < random_r_delay [31:0] $end
$var integer 32 = random_w_delay [31:0] $end
$scope begin $ivl_for_loop1 $end
$var integer 32 > i [31:0] $end
$upscope $end
$scope begin $ivl_for_loop2 $end
$var integer 32 ? i [31:0] $end
$upscope $end
$scope begin $ivl_for_loop3 $end
$var integer 32 @ i [31:0] $end
$upscope $end
$upscope $end
$scope task read_fifo $end
$var reg 32 A test_dout [31:0] $end
$upscope $end
$scope task write_fifo $end
$var reg 32 B test_din [31:0] $end
$upscope $end
$upscope $end
$scope module tb_async_fifo $end
$scope module dut $end
$var reg 32 C \fifo[0] [31:0] $end
$upscope $end
$upscope $end
$scope module tb_async_fifo $end
$scope module dut $end
$var reg 32 D \fifo[1] [31:0] $end
$upscope $end
$upscope $end
$scope module tb_async_fifo $end
$scope module dut $end
$var reg 32 E \fifo[2] [31:0] $end
$upscope $end
$upscope $end
$scope module tb_async_fifo $end
$scope module dut $end
$var reg 32 F \fifo[3] [31:0] $end
$upscope $end
$upscope $end
$scope module tb_async_fifo $end
$scope module dut $end
$var reg 32 G \fifo[4] [31:0] $end
$upscope $end
$upscope $end
$scope module tb_async_fifo $end
$scope module dut $end
$var reg 32 H \fifo[5] [31:0] $end
$upscope $end
$upscope $end
$scope module tb_async_fifo $end
$scope module dut $end
$var reg 32 I \fifo[6] [31:0] $end
$upscope $end
$upscope $end
$scope module tb_async_fifo $end
$scope module dut $end
$var reg 32 J \fifo[7] [31:0] $end
$upscope $end
$upscope $end
$enddefinitions $end
$comment Show the parameter values. $end
$dumpall
b100000 0
b11 /
b1000 .
b100000 %
b1000 $
$end
#0
$dumpvars
b0 J
b0 I
b0 H
b0 G
b0 F
b0 E
b0 D
b0 C
bx B
bx A
b0 @
b0 ?
b1000 >
b0 =
b0 <
bx ;
bx :
b1000 9
b0 8
b0 7
b0 6
b0 5
b0 4
b0 3
b0 2
b0 1
b0 -
b0 ,
1+
0*
1)
0(
0'
b0 &
b0 #
1"
0!
$end
#5000
1(
#10000
b0 J
b0 I
b0 H
b0 G
b0 F
b0 E
b0 D
b0 C
b1000 9
0(
1*
#15000
1(
#20000
0(
0*
#25000
b1100100 &
b1100100 ,
0+
b1100100 B
b1100100 ;
1'
1(
#30000
b1100101 C
b1100101 #
b1100101 -
b1 4
b1 2
b1100101 &
b1100101 ,
b1100101 B
b1 ?
b1100101 ;
0(
1*
#35000
b1 8
1(
#40000
0(
0*
#45000
0"
b1 7
1(
#50000
b1100110 D
b11 4
b10 2
b1100110 &
b1100110 ,
b1100110 B
b10 ?
b1100110 ;
0(
1*
#55000
b11 8
1(
#60000
0(
0*
#65000
b11 7
1(
#70000
b1100111 E
b10 4
b11 2
b1100111 &
b1100111 ,
b1100111 B
b11 ?
b1100111 ;
0(
1*
#75000
b10 8
1(
#80000
0(
0*
#85000
b10 7
1(
#90000
b1101000 F
b110 4
b100 2
b1101000 &
b1101000 ,
b1101000 B
b100 ?
b1101000 ;
0(
1*
#95000
b110 8
1(
#100000
0(
0*
#105000
b110 7
1(
#110000
b1101001 G
b111 4
b101 2
b1101001 &
b1101001 ,
b1101001 B
b101 ?
b1101001 ;
0(
1*
#115000
b111 8
1(
#120000
0(
0*
#125000
b111 7
1(
#130000
b1101010 H
b101 4
b110 2
b1101010 &
b1101010 ,
b1101010 B
b110 ?
b1101010 ;
0(
1*
#135000
b101 8
1(
#140000
0(
0*
#145000
b101 7
1(
#150000
b1101011 I
b100 4
b111 2
b1101011 &
b1101011 ,
b1101011 B
b111 ?
b1101011 ;
0(
1*
#155000
b100 8
1(
#160000
0(
0*
#165000
b100 7
1(
#170000
1!
b1101100 J
b1100 4
b1000 2
b1101100 &
b1101100 ,
b1101100 B
b1000 ?
b1101100 ;
0(
1*
#175000
b1100 8
1(
#180000
0(
0*
#185000
b1100 7
1(
#190000
1+
b1001 ?
0(
1*
#195000
1(
#200000
0(
0*
#205000
1(
#210000
b1010 ?
0(
1*
#215000
1(
#220000
0(
0*
#225000
1(
#230000
b1011 ?
0(
1*
#235000
1(
#240000
0(
0*
#245000
1(
#250000
b1100 ?
0(
1*
#255000
1(
#260000
0(
0*
#265000
1(
#270000
b1101 ?
0(
1*
#275000
1(
#280000
0(
0*
#285000
1(
#290000
b1110 ?
0(
1*
#295000
1(
#300000
0(
0*
#305000
1(
#310000
b1111 ?
0(
1*
#315000
1(
#320000
0(
0*
#325000
1(
#330000
b10000 ?
0(
1*
#335000
1(
#340000
0(
0*
#345000
1(
#350000
b10001 ?
0(
1*
#355000
1(
#360000
0(
0*
#365000
1(
#370000
0)
b10010 ?
0(
1*
#375000
b1100110 #
b1100110 -
b1 3
b1 1
b1 @
b1100101 :
b1100101 A
1(
#380000
0(
0*
#385000
b1100111 #
b1100111 -
b11 3
b10 1
b10 @
b1100110 :
b1100110 A
1(
#390000
b11 6
0(
1*
#395000
b1101000 #
b1101000 -
b10 3
b11 1
b11 @
b1100111 :
b1100111 A
1(
#400000
0(
0*
#405000
b1101001 #
b1101001 -
b110 3
b100 1
b100 @
b1101000 :
b1101000 A
1(
#410000
0!
b11 5
b110 6
0(
1*
#415000
b1101010 #
b1101010 -
b111 3
b101 1
b101 @
b1101001 :
b1101001 A
1(
#420000
0(
0*
#425000
b1101011 #
b1101011 -
b101 3
b110 1
b110 @
b1101010 :
b1101010 A
1(
#430000
b110 5
b101 6
0(
1*
#435000
b1101100 #
b1101100 -
b100 3
b111 1
b111 @
b1101011 :
b1101011 A
1(
#440000
0(
0*
#445000
b1100101 #
b1100101 -
1"
b1100 3
b1000 1
b1000 @
b1101100 :
b1101100 A
1(
#450000
b101 5
b1100 6
0(
1*
#455000
1)
b1001 @
b1100101 :
b1100101 A
1(
#460000
0(
0*
#465000
b1010 @
1(
#470000
b1100 5
0(
1*
#475000
b1011 @
1(
#480000
0(
0*
#485000
b1100 @
1(
#490000
0(
1*
#495000
b1101 @
1(
#500000
0(
0*
#505000
b1110 @
1(
#510000
0(
1*
#515000
b1111 @
1(
#520000
0(
0*
#525000
b10000 @
1(
#530000
0(
1*
#535000
b10001 @
1(
#540000
0(
0*
#545000
b0 J
b0 I
b0 H
b0 G
b0 F
b0 E
b0 D
b0 C
b0 #
b0 -
b0 5
b0 6
b0 4
b0 2
b0 7
b0 8
1"
b0 3
b0 1
b1000 9
0'
b10010 @
1(
#550000
b0 J
b0 I
b0 H
b0 G
b0 F
b0 E
b0 D
b0 C
b1000 9
0(
1*
#555000
1(
#560000
0(
0*
#565000
1(
#570000
b0 J
b0 I
b0 H
b0 G
b0 F
b0 E
b0 D
b0 C
b1000 9
0(
1*
#575000
0+
1'
1(
#580000
0(
0*
#585000
1(
#590000
b1101101 C
b1101101 #
b1101101 -
b1 4
b1 2
b1101101 &
b1101101 ,
b1101101 B
b1101101 ;
0(
1*
#595000
b1 8
1(
#600000
0(
0*
#605000
0"
b1 7
1(
#610000
b1101110 D
b11 4
b10 2
b1101110 &
b1101110 ,
b1101110 B
b1101110 ;
0(
1*
#615000
b1101110 #
b1101110 -
1"
b1 3
b1 1
b11 8
0)
1(
#620000
0(
0*
#625000
0"
b11 7
1)
b1101110 :
b1101110 A
1(
#630000
b1 6
b1101111 E
b10 4
b11 2
b1101111 &
b1101111 ,
b1101111 B
b1101111 ;
0(
1*
#635000
b1101111 #
b1101111 -
1"
b11 3
b10 1
b10 8
0)
1(
#640000
0(
0*
#645000
0"
b10 7
1)
b1101111 :
b1101111 A
1(
#650000
b1110000 F
b110 4
b100 2
b1 5
b11 6
b1110000 &
b1110000 ,
b1110000 B
b1110000 ;
0(
1*
#655000
b1110000 #
b1110000 -
1"
b10 3
b11 1
b110 8
0)
1(
#660000
0(
0*
#665000
0"
b110 7
1)
b1110000 :
b1110000 A
1(
#670000
b11 5
b10 6
b1110001 G
b111 4
b101 2
b1110001 &
b1110001 ,
b1110001 B
b1110001 ;
0(
1*
#675000
b1110001 #
b1110001 -
1"
b110 3
b100 1
b111 8
0)
1(
#680000
0(
0*
#685000
0"
b111 7
1)
b1110001 :
b1110001 A
1(
#690000
b1110010 H
b101 4
b110 2
b10 5
b110 6
b1110010 &
b1110010 ,
b1110010 B
b1110010 ;
0(
1*
#695000
b1110010 #
b1110010 -
1"
b111 3
b101 1
b101 8
0)
1(
#700000
0(
0*
#705000
0"
b101 7
1)
b1110010 :
b1110010 A
1(
#710000
b110 5
b111 6
b1110011 I
b100 4
b111 2
b1110011 &
b1110011 ,
b1110011 B
b1110011 ;
0(
1*
#715000
b1110011 #
b1110011 -
1"
b101 3
b110 1
b100 8
0)
1(
#720000
0(
0*
#725000
0"
b100 7
1)
b1110011 :
b1110011 A
1(
#730000
b1110100 J
b1100 4
b1000 2
b111 5
b101 6
b1110100 &
b1110100 ,
b1110100 B
b1110100 ;
0(
1*
#735000
b1110100 #
b1110100 -
1"
b100 3
b111 1
b1100 8
0)
1(
#740000
0(
0*
#745000
0"
b1100 7
1)
b1110100 :
b1110100 A
1(
#750000
b101 5
b100 6
b1110101 C
b1101 4
b1001 2
b1110101 &
b1110101 ,
b1110101 B
b1110101 ;
0(
1*
#755000
b1110101 #
b1110101 -
1"
b1100 3
b1000 1
b1101 8
0)
1(
#760000
0(
0*
#765000
0"
b1101 7
1)
b1110101 :
b1110101 A
1(
#770000
b1110110 D
b1111 4
b1010 2
b100 5
b1100 6
b1110110 &
b1110110 ,
b1110110 B
b1110110 ;
0(
1*
#775000
b1110110 #
b1110110 -
1"
b1101 3
b1001 1
b1111 8
0)
1(
#780000
0(
0*
#785000
0"
b1111 7
1)
b1110110 :
b1110110 A
1(
#790000
b1100 5
b1101 6
b1110111 E
b1110 4
b1011 2
b1110111 &
b1110111 ,
b1110111 B
b1110111 ;
0(
1*
#795000
b1110111 #
b1110111 -
1"
b1111 3
b1010 1
b1110 8
0)
1(
#800000
0(
0*
#805000
0"
b1110 7
1)
b1110111 :
b1110111 A
1(
#810000
b1111000 F
b1010 4
b1100 2
b1101 5
b1111 6
b1111000 &
b1111000 ,
b1111000 B
b1111000 ;
0(
1*
#815000
b1111000 #
b1111000 -
1"
b1110 3
b1011 1
b1010 8
0)
1(
#820000
0(
0*
#825000
0"
b1010 7
1)
b1111000 :
b1111000 A
1(
#830000
b1111 5
b1110 6
b1111001 G
b1011 4
b1101 2
b1111001 &
b1111001 ,
b1111001 B
b1111001 ;
0(
1*
#835000
b1111001 #
b1111001 -
1"
b1010 3
b1100 1
b1011 8
0)
1(
#840000
0(
0*
#845000
0"
b1011 7
1)
b1111001 :
b1111001 A
1(
#850000
b1111010 H
b1001 4
b1110 2
b1110 5
b1010 6
b1111010 &
b1111010 ,
b1111010 B
b1111010 ;
0(
1*
#855000
b1111010 #
b1111010 -
1"
b1011 3
b1101 1
b1001 8
0)
1(
#860000
0(
0*
#865000
0"
b1001 7
1)
b1111010 :
b1111010 A
1(
#870000
b1010 5
b1011 6
b1111011 I
b1000 4
b1111 2
b1111011 &
b1111011 ,
b1111011 B
b1111011 ;
0(
1*
#875000
b1111011 #
b1111011 -
1"
b1001 3
b1110 1
b1000 8
0)
1(
#880000
0(
0*
#885000
0"
b1000 7
1)
b1111011 :
b1111011 A
1(
#890000
b1111100 J
b0 2
b1011 5
b1001 6
b1111100 &
b1111100 ,
b1111100 B
b1111100 ;
0(
1*
#895000
b1111100 #
b1111100 -
1"
b1000 3
b1111 1
0)
1(
#900000
0(
0*
#905000
1)
b1111100 :
b1111100 A
1(
#910000
b1001 5
b1000 6
b1111101 C
b1 4
b1 2
b1111101 &
b1111101 ,
b1111101 B
b1111101 ;
0(
1*
#915000
b1 8
1(
#920000
0(
0*
#925000
0"
b1 7
1(
#930000
b1111110 D
b11 4
b10 2
b1000 5
b1111110 &
b1111110 ,
b1111110 B
b1111110 ;
0(
1*
#935000
b1111101 #
b1111101 -
b0 1
b11 8
0)
1(
#940000
0(
0*
#945000
b1111110 #
b1111110 -
b11 7
0"
b1 3
b1 1
b1111101 :
b1111101 A
1(
#950000
b1 6
b1111111 E
b10 4
b11 2
b1111111 &
b1111111 ,
b1111111 B
b1111111 ;
0(
1*
#955000
b1111111 #
b1111111 -
1"
b11 3
b10 1
b10 8
b1111110 :
b1111110 A
1(
#960000
0(
0*
#965000
0"
b10 7
1)
b1111111 :
b1111111 A
1(
#970000
b10000000 F
b110 4
b100 2
b1 5
b11 6
b10000000 &
b10000000 ,
b10000000 B
b10000000 ;
0(
1*
#975000
b10000000 #
b10000000 -
1"
b10 3
b11 1
b110 8
0)
1(
#980000
0(
0*
#985000
0"
b110 7
1)
b10000000 :
b10000000 A
1(
#990000
b11 5
b10 6
b10000001 G
b111 4
b101 2
b10000001 &
b10000001 ,
b10000001 B
b10000001 ;
0(
1*
#995000
b10000001 #
b10000001 -
1"
b110 3
b100 1
b111 8
0)
1(
#1000000
0(
0*
#1005000
0"
b111 7
1)
b10000001 :
b10000001 A
1(
#1010000
b10000010 H
b101 4
b110 2
b10 5
b110 6
b10000010 &
b10000010 ,
b10000010 B
b10000010 ;
0(
1*
#1015000
b10000010 #
b10000010 -
1"
b111 3
b101 1
b101 8
0)
1(
#1020000
0(
0*
#1025000
0"
b101 7
1)
b10000010 :
b10000010 A
1(
#1030000
b110 5
b111 6
b10000011 I
b100 4
b111 2
b10000011 &
b10000011 ,
b10000011 B
b10000011 ;
0(
1*
#1035000
b10000011 #
b10000011 -
1"
b101 3
b110 1
b100 8
0)
1(
#1040000
0(
0*
#1045000
0"
b100 7
1)
b10000011 :
b10000011 A
1(
#1050000
b10000100 J
b1100 4
b1000 2
b111 5
b101 6
b10000100 &
b10000100 ,
b10000100 B
b10000100 ;
0(
1*
#1055000
b10000100 #
b10000100 -
1"
b100 3
b111 1
b1100 8
0)
1(
#1060000
0(
0*
#1065000
0"
b1100 7
1)
b10000100 :
b10000100 A
1(
#1070000
b101 5
b100 6
b10000101 C
b1101 4
b1001 2
b10000101 &
b10000101 ,
b10000101 B
b10000101 ;
0(
1*
#1075000
b10000101 #
b10000101 -
1"
b1100 3
b1000 1
b1101 8
0)
1(
#1080000
0(
0*
#1085000
0"
b1101 7
1)
b10000101 :
b10000101 A
1(
#1090000
b10000110 D
b1111 4
b1010 2
b100 5
b1100 6
b10000110 &
b10000110 ,
b10000110 B
b10000110 ;
0(
1*
#1095000
b10000110 #
b10000110 -
1"
b1101 3
b1001 1
b1111 8
0)
1(
#1100000
0(
0*
#1105000
0"
b1111 7
1)
b10000110 :
b10000110 A
1(
#1110000
b1100 5
b1101 6
b10000111 E
b1110 4
b1011 2
b10000111 &
b10000111 ,
b10000111 B
b10000111 ;
0(
1*
#1115000
b10000111 #
b10000111 -
1"
b1111 3
b1010 1
b1110 8
0)
1(
#1120000
0(
0*
#1125000
0"
b1110 7
1)
b10000111 :
b10000111 A
1(
#1130000
b10001000 F
b1010 4
b1100 2
b1101 5
b1111 6
b10001000 &
b10001000 ,
b10001000 B
b10001000 ;
0(
1*
#1135000
b10001000 #
b10001000 -
1"
b1110 3
b1011 1
b1010 8
0)
1(
#1140000
0(
0*
#1145000
0"
b1010 7
1)
b10001000 :
b10001000 A
1(
#1150000
b1111 5
b1110 6
b10001001 G
b1011 4
b1101 2
b10001001 &
b10001001 ,
b10001001 B
b10001001 ;
0(
1*
#1155000
b10001001 #
b10001001 -
1"
b1010 3
b1100 1
b1011 8
0)
1(
#1160000
0(
0*
#1165000
0"
b1011 7
1)
b10001001 :
b10001001 A
1(
#1170000
b10001010 H
b1001 4
b1110 2
b1110 5
b1010 6
b10001010 &
b10001010 ,
b10001010 B
b10001010 ;
0(
1*
#1175000
b10001010 #
b10001010 -
1"
b1011 3
b1101 1
b1001 8
0)
1(
#1180000
0(
0*
#1185000
0"
b1001 7
1)
b10001010 :
b10001010 A
1(
#1190000
b1010 5
b1011 6
b10001011 I
b1000 4
b1111 2
b10001011 &
b10001011 ,
b10001011 B
b10001011 ;
0(
1*
#1195000
b10001011 #
b10001011 -
1"
b1001 3
b1110 1
b1000 8
0)
1(
#1200000
0(
0*
#1205000
0"
b1000 7
1)
b10001011 :
b10001011 A
1(
#1210000
b10001100 J
b0 2
b1011 5
b1001 6
b10001100 &
b10001100 ,
b10001100 B
b10001100 ;
0(
1*
#1215000
b10001100 #
b10001100 -
1"
b1000 3
b1111 1
0)
1(
#1220000
0(
0*
#1225000
1)
b10001100 :
b10001100 A
1(
#1230000
b1001 5
b1000 6
b10001101 C
b1 4
b1 2
b10001101 &
b10001101 ,
b10001101 B
b10001101 ;
0(
1*
#1235000
b1 8
1(
#1240000
0(
0*
#1245000
0"
b1 7
1(
#1250000
b10001110 D
b11 4
b10 2
b1000 5
b10001110 &
b10001110 ,
b10001110 B
b10001110 ;
0(
1*
#1255000
b10001101 #
b10001101 -
b0 1
b11 8
0)
1(
#1260000
0(
0*
#1265000
b10001110 #
b10001110 -
b11 7
0"
b1 3
b1 1
b10001101 :
b10001101 A
1(
#1270000
b1 6
b10001111 E
b10 4
b11 2
b10001111 &
b10001111 ,
b10001111 B
b10001111 ;
0(
1*
#1275000
b10001111 #
b10001111 -
1"
b11 3
b10 1
b10 8
b10001110 :
b10001110 A
1(
#1280000
0(
0*
#1285000
0"
b10 7
1)
b10001111 :
b10001111 A
1(
#1290000
b10010000 F
b110 4
b100 2
b1 5
b11 6
b10010000 &
b10010000 ,
b10010000 B
b10010000 ;
0(
1*
#1295000
b10010000 #
b10010000 -
1"
b10 3
b11 1
b110 8
0)
1(
#1300000
0(
0*
#1305000
0"
b110 7
1)
b10010000 :
b10010000 A
1(
#1310000
b11 5
b10 6
b10010001 G
b111 4
b101 2
b10010001 &
b10010001 ,
b10010001 B
b10010001 ;
0(
1*
#1315000
b10010001 #
b10010001 -
1"
b110 3
b100 1
b111 8
0)
1(
#1320000
0(
0*
#1325000
0"
b111 7
1)
b10010001 :
b10010001 A
1(
#1330000
b10010010 H
b101 4
b110 2
b10 5
b110 6
b10010010 &
b10010010 ,
b10010010 B
b10010010 ;
0(
1*
#1335000
b10010010 #
b10010010 -
1"
b111 3
b101 1
b101 8
0)
1(
#1340000
0(
0*
#1345000
0"
b101 7
1)
b10010010 :
b10010010 A
1(
#1350000
b110 5
b111 6
b10010011 I
b100 4
b111 2
b10010011 &
b10010011 ,
b10010011 B
b10010011 ;
0(
1*
#1355000
b10010011 #
b10010011 -
1"
b101 3
b110 1
b100 8
0)
1(
#1360000
0(
0*
#1365000
0"
b100 7
1)
b10010011 :
b10010011 A
1(
#1370000
b10010100 J
b1100 4
b1000 2
b111 5
b101 6
b10010100 &
b10010100 ,
b10010100 B
b10010100 ;
0(
1*
#1375000
b10010100 #
b10010100 -
1"
b100 3
b111 1
b1100 8
0)
1(
#1380000
0(
0*
#1385000
0"
b1100 7
1)
b10010100 :
b10010100 A
1(
#1390000
b101 5
b100 6
b10010101 C
b1101 4
b1001 2
b10010101 &
b10010101 ,
b10010101 B
b10010101 ;
0(
1*
#1395000
b10010101 #
b10010101 -
1"
b1100 3
b1000 1
b1101 8
0)
1(
#1400000
0(
0*
#1405000
0"
b1101 7
1)
b10010101 :
b10010101 A
1(
#1410000
b10010110 D
b1111 4
b1010 2
b100 5
b1100 6
b10010110 &
b10010110 ,
b10010110 B
b10010110 ;
0(
1*
#1415000
b10010110 #
b10010110 -
1"
b1101 3
b1001 1
b1111 8
0)
1(
#1420000
0(
0*
#1425000
0"
b1111 7
1)
b10010110 :
b10010110 A
1(
#1430000
b1100 5
b1101 6
b10010111 E
b1110 4
b1011 2
b10010111 &
b10010111 ,
b10010111 B
b10010111 ;
0(
1*
#1435000
b10010111 #
b10010111 -
1"
b1111 3
b1010 1
b1110 8
0)
1(
#1440000
0(
0*
#1445000
0"
b1110 7
1)
b10010111 :
b10010111 A
1(
#1450000
b10011000 F
b1010 4
b1100 2
b1101 5
b1111 6
b10011000 &
b10011000 ,
b10011000 B
b10011000 ;
0(
1*
#1455000
b10011000 #
b10011000 -
1"
b1110 3
b1011 1
b1010 8
0)
1(
#1460000
0(
0*
#1465000
0"
b1010 7
1)
b10011000 :
b10011000 A
1(
#1470000
b1111 5
b1110 6
b10011001 G
b1011 4
b1101 2
b10011001 &
b10011001 ,
b10011001 B
b10011001 ;
0(
1*
#1475000
b10011001 #
b10011001 -
1"
b1010 3
b1100 1
b1011 8
0)
1(
#1480000
0(
0*
#1485000
0"
b1011 7
1)
b10011001 :
b10011001 A
1(
#1490000
b10011010 H
b1001 4
b1110 2
b1110 5
b1010 6
b10011010 &
b10011010 ,
b10011010 B
b10011010 ;
0(
1*
#1495000
b10011010 #
b10011010 -
1"
b1011 3
b1101 1
b1001 8
0)
1(
#1500000
0(
0*
#1505000
0"
b1001 7
1)
b10011010 :
b10011010 A
1(
#1510000
b1010 5
b1011 6
b10011011 I
b1000 4
b1111 2
b10011011 &
b10011011 ,
b10011011 B
b10011011 ;
0(
1*
#1515000
b10011011 #
b10011011 -
1"
b1001 3
b1110 1
b1000 8
0)
1(
#1520000
0(
0*
#1525000
0"
b1000 7
1)
b10011011 :
b10011011 A
1(
#1530000
b10011100 J
b0 2
b1011 5
b1001 6
b10011100 &
b10011100 ,
b10011100 B
b10011100 ;
0(
1*
#1535000
b10011100 #
b10011100 -
1"
b1000 3
b1111 1
0)
1(
#1540000
0(
0*
#1545000
1)
b10011100 :
b10011100 A
1(
#1550000
b1001 5
b1000 6
b10011101 C
b1 4
b1 2
b10011101 &
b10011101 ,
b10011101 B
b10011101 ;
0(
1*
#1555000
b1 8
1(
#1560000
0(
0*
#1565000
0"
b1 7
1(
#1570000
b10011110 D
b11 4
b10 2
b1000 5
b10011110 &
b10011110 ,
b10011110 B
b10011110 ;
0(
1*
