mux/mux.sv
// Simple mux

module mux #(
  parameter BITS = 16
)(
  input logic clk,
  input logic n_rst,
  input logic [$clog2(BITS) - 1:0] s,    // selector inputs
  input logic [BITS - 1:0] i,   // signal inputs
  output logic z
);

  always_ff @(posedge clk, negedge n_rst) begin
    if (~n_rst) begin
      z <= 1'b0;
    end else begin
      z <= i[s];
    end
  end
  
endmodule

mux/tb_mux.sv
`timescale 1ns/1ps

module mux_tb;

  parameter BITS = 32;

  // 1. Declare local signals to connect to the Design Under Test (DUT)
  logic clk;
  logic n_rst;
  logic [$clog2(BITS) - 1:0] s;
  logic [BITS - 1:0] i;
  logic z;

  // 2. Instantiate the DUT (Design Under Test)
  mux #(BITS) dut (.*);

  // 3. Clock Generation (50MHz clock -> 20ns period)
  initial clk = 0;
  always #(10ns) clk = ~clk;


  int hit_cnt = 0;
  int miss_cnt = 0;

  // 4. Stimulus Generation
  initial begin
    // Optional: Enable wave dumping for EDA Playground EPWave viewer
    $dumpfile("dump.vcd");
    $dumpvars(0, mux_tb);

    // Initialize inputs
    n_rst = 0;
    s = 4'h0;
    i = 0;

    // Hold reset for 2 clock cycles
    @(posedge clk);
    @(posedge clk);
    n_rst = 1; // Release reset
    
    $display("--- Starting MUX Tests ---");

    for (int round=0; round<100; round++) begin
      hit_cnt = 0;
      miss_cnt = 0;
      i = $urandom();
      for (logic[4:0] sel=0; sel<16; sel++) begin
        s = sel[3:0];
        #5ns;
        @(posedge clk);
        $display("Testing s = %d, Random i: %b", s, i);
        if (z === i[s]) begin
          hit_cnt++;
        end else begin
          miss_cnt++;
          $error("Mismatch found at Round %0d, s = %0d! Expected %b, Got %b", round, s, i[s], z);
        end
      end
      $display("=== Round %0d Results ===", round);
      $display("Hits:   %0d", hit_cnt);
      $display("Misses: %0d", miss_cnt);
    end

    #20;
    $display("--- Tests Complete ---");
    $finish;

  end
endmodule

mux/dump.vcd
$date
	Sat May 23 11:46:22 2026
$end
$version
	Icarus Verilog
$end
$timescale
	1ps
$end
$scope module mux_tb $end
$var wire 1 ! z $end
$var parameter 32 " BITS $end
$var reg 1 # clk $end
$var reg 32 $ i [31:0] $end
$var reg 1 % n_rst $end
$var reg 5 & s [4:0] $end
$var integer 32 ' hit_cnt [31:0] $end
$var integer 32 ( miss_cnt [31:0] $end
$scope module dut $end
$var wire 1 # clk $end
$var wire 32 ) i [31:0] $end
$var wire 1 % n_rst $end
$var wire 5 * s [4:0] $end
$var parameter 32 + BITS $end
$var reg 1 ! z $end
$upscope $end
$scope begin $ivl_for_loop0 $end
$var integer 32 , round [31:0] $end
$scope begin $ivl_for_loop1 $end
$var reg 5 - sel [4:0] $end
$upscope $end
$upscope $end
$upscope $end
$enddefinitions $end
$comment Show the parameter values. $end
$dumpall
b100000 +
b100000 "
$end
#0
$dumpvars
bx -
b0 ,
b0 *
b0 )
b0 (
b0 '
b0 &
0%
b0 $
0#
0!
$end
#10000
1#
#20000
0#
#30000
b0 -
b10010010000101010011010100100100 $
b10010010000101010011010100100100 )
1%
1#
#40000
0#
#50000
b1 &
b1 *
b1 -
b1 '
1#
#60000
0#
#70000
1!
b10 &
b10 *
b10 -
b10 '
1#
#80000
0#
#90000
0!
b11 &
b11 *
b11 -
b11 '
1#
#100000
0#
#110000
b100 &
b100 *
b100 -
b100 '
1#
#120000
0#
#130000
1!
b101 &
b101 *
b101 -
b101 '
1#
#140000
0#
#150000
0!
b110 &
b110 *
b110 -
b110 '
1#
#160000
0#
#170000
b111 &
b111 *
b111 -
b111 '
1#
#180000
0#
#190000
1!
b1000 &
b1000 *
b1000 -
b1000 '
1#
#200000
0#
#210000
0!
b1001 &
b1001 *
b1001 -
b1001 '
1#
#220000
0#
#230000
1!
b1010 &
b1010 *
b1010 -
b1010 '
1#
#240000
0#
#250000
0!
b1011 &
b1011 *
b1011 -
b1011 '
1#
#260000
0#
#270000
1!
b1100 &
b1100 *
b1100 -
b1100 '
1#
#280000
0#
#290000
b1101 &
b1101 *
b1101 -
b1101 '
1#
#300000
0#
#310000
0!
b1110 &
b1110 *
b1110 -
b1110 '
1#
#320000
0#
#330000
b1111 &
b1111 *
b1111 -
b1111 '
1#
#340000
0#
#350000
1!
b0 &
b0 *
b1000000100010010101111010000001 $
b1000000100010010101111010000001 )
b1 ,
b0 -
b0 '
1#
#360000
0#
#370000
0!
b1 &
b1 *
b1 -
b1 '
1#
#380000
0#
#390000
b10 &
b10 *
b10 -
b10 '
1#
#400000
0#
#410000
b11 &
b11 *
b11 -
b11 '
1#
#420000
0#
#430000
b100 &
b100 *
b100 -
b100 '
1#
#440000
0#
#450000
b101 &
b101 *
b101 -
b101 '
1#
#460000
0#
#470000
b110 &
b110 *
b110 -
b110 '
1#
#480000
0#
#490000
1!
b111 &
b111 *
b111 -
b111 '
1#
#500000
0#
#510000
0!
b1000 &
b1000 *
b1000 -
b1000 '
1#
#520000
0#
#530000
1!
b1001 &
b1001 *
b1001 -
b1001 '
1#
#540000
0#
#550000
b1010 &
b1010 *
b1010 -
b1010 '
1#
#560000
0#
#570000
b1011 &
b1011 *
b1011 -
b1011 '
1#
#580000
0#
#590000
b1100 &
b1100 *
b1100 -
b1100 '
1#
#600000
0#
#610000
0!
b1101 &
b1101 *
b1101 -
b1101 '
1#
#620000
0#
#630000
1!
b1110 &
b1110 *
b1110 -
b1110 '
1#
#640000
0#
#650000
0!
b1111 &
b1111 *
b1111 -
b1111 '
1#
#660000
0#
#670000
1!
b0 &
b0 *
b100100001001101011000001001 $
b100100001001101011000001001 )
b10 ,
b0 -
b0 '
1#
#680000
0#
#690000
0!
b1 &
b1 *
b1 -
b1 '
1#
#700000
0#
#710000
b10 &
b10 *
b10 -
b10 '
1#
#720000
0#
#730000
1!
b11 &
b11 *
b11 -
b11 '
1#
#740000
0#
#750000
0!
b100 &
b100 *
b100 -
b100 '
1#
#760000
0#
#770000
b101 &
b101 *
b101 -
b101 '
1#
#780000
0#
#790000
b110 &
b110 *
b110 -
b110 '
1#
#800000
0#
#810000
b111 &
b111 *
b111 -
b111 '
1#
#820000
0#
#830000
b1000 &
b1000 *
b1000 -
b1000 '
1#
#840000
0#
#850000
1!
b1001 &
b1001 *
b1001 -
b1001 '
1#
#860000
0#
#870000
b1010 &
b1010 *
b1010 -
b1010 '
1#
#880000
0#
#890000
0!
b1011 &
b1011 *
b1011 -
b1011 '
1#
#900000
0#
#910000
1!
b1100 &
b1100 *
b1100 -
b1100 '
1#
#920000
0#
#930000
0!
b1101 &
b1101 *
b1101 -
b1101 '
1#
#940000
0#
#950000
1!
b1110 &
b1110 *
b1110 -
b1110 '
1#
#960000
0#
#970000
b1111 &
b1111 *
b1111 -
b1111 '
1#
#980000
0#
#990000
b0 &
b0 *
b110001111100000101011001100011 $
b110001111100000101011001100011 )
b11 ,
b0 -
b0 '
1#
#1000000
0#
#1010000
b1 &
b1 *
b1 -
b1 '
1#
#1020000
0#
#1030000
0!
b10 &
b10 *
b10 -
b10 '
1#
#1040000
0#
#1050000
b11 &
b11 *
b11 -
b11 '
1#
#1060000
0#
#1070000
b100 &
b100 *
b100 -
b100 '
1#
#1080000
0#
#1090000
1!
b101 &
b101 *
b101 -
b101 '
1#
#1100000
0#
#1110000
b110 &
b110 *
b110 -
b110 '
1#
#1120000
0#
#1130000
0!
b111 &
b111 *
b111 -
b111 '
1#
#1140000
0#
#1150000
b1000 &
b1000 *
b1000 -
b1000 '
1#
#1160000
0#
#1170000
1!
b1001 &
b1001 *
b1001 -
b1001 '
1#
#1180000
0#
#1190000
b1010 &
b1010 *
b1010 -
b1010 '
1#
#1200000
0#
#1210000
0!
b1011 &
b1011 *
b1011 -
b1011 '
1#
#1220000
0#
#1230000
1!
b1100 &
b1100 *
b1100 -
b1100 '
1#
#1240000
0#
#1250000
0!
b1101 &
b1101 *
b1101 -
b1101 '
1#
#1260000
0#
#1270000
1!
b1110 &
b1110 *
b1110 -
b1110 '
1#
#1280000
0#
#1290000
0!
b1111 &
b1111 *
b1111 -
b1111 '
1#
#1300000
0#
#1310000
1!
b0 &
b0 *
b10000110101110010111101100001101 $
b10000110101110010111101100001101 )
b100 ,
b0 -
b0 '
1#
#1320000
0#
#1330000
0!
b1 &
b1 *
b1 -
b1 '
1#
#1340000
0#
#1350000
1!
b10 &
b10 *
b10 -
b10 '
1#
#1360000
0#
#1370000
b11 &
b11 *
b11 -
b11 '
1#
#1380000
0#
#1390000
0!
b100 &
b100 *
b100 -
b100 '
1#
#1400000
0#
#1410000
b101 &
b101 *
b101 -
b101 '
1#
#1420000
0#
#1430000
b110 &
b110 *
b110 -
b110 '
1#
#1440000
0#
#1450000
b111 &
b111 *
b111 -
b111 '
1#
#1460000
0#
#1470000
1!
b1000 &
b1000 *
b1000 -
b1000 '
1#
#1480000
0#
#1490000
b1001 &
b1001 *
b1001 -
b1001 '
1#
#1500000
0#
#1510000
0!
b1010 &
b1010 *
b1010 -
b1010 '
1#
#1520000
0#
#1530000
1!
b1011 &
b1011 *
b1011 -
b1011 '
1#
#1540000
0#
#1550000
b1100 &
b1100 *
b1100 -
b1100 '
1#
#1560000
0#
#1570000
b1101 &
b1101 *
b1101 -
b1101 '
1#
#1580000
0#
#1590000
b1110 &
b1110 *
b1110 -
b1110 '
1#
#1600000
0#
#1610000
0!
b1111 &
b1111 *
b1111 -
b1111 '
1#
#1620000
0#
#1630000
1!
b0 &
b0 *
b11000110110111111001100110001101 $
b11000110110111111001100110001101 )
b101 ,
b0 -
b0 '
1#
#1640000
0#
#1650000
0!
b1 &
b1 *
b1 -
b1 '
1#
#1660000
0#
#1670000
1!
b10 &
b10 *
b10 -
b10 '
1#
#1680000
0#
#1690000
b11 &
b11 *
b11 -
b11 '
1#
#1700000
0#
#1710000
0!
b100 &
b100 *
b100 -
b100 '
1#
#1720000
0#
#1730000
b101 &
b101 *
b101 -
b101 '
1#
#1740000
0#
#1750000
b110 &
b110 *
b110 -
b110 '
1#
#1760000
0#
#1770000
1!
b111 &
b111 *
b111 -
b111 '
1#
#1780000
0#
#1790000
b1000 &
b1000 *
b1000 -
b1000 '
1#
#1800000
0#
#1810000
0!
b1001 &
b1001 *
b1001 -
b1001 '
1#
#1820000
0#
#1830000
b1010 &
b1010 *
b1010 -
b1010 '
1#
#1840000
0#
#1850000
1!
b1011 &
b1011 *
b1011 -
b1011 '
1#
#1860000
0#
#1870000
b1100 &
b1100 *
b1100 -
b1100 '
1#
#1880000
0#
#1890000
0!
b1101 &
b1101 *
b1101 -
b1101 '
1#
#1900000
0#
#1910000
b1110 &
b1110 *
b1110 -
b1110 '
1#
#1920000
0#
#1930000
1!
b1111 &
b1111 *
b1111 -
b1111 '
1#
#1940000
0#
#1950000
b0 &
b0 *
b110010110000101000010001100101 $
b110010110000101000010001100101 )
b110 ,
b0 -
b0 '
1#
#1960000
0#
#1970000
0!
b1 &
b1 *
b1 -
b1 '
1#
#1980000
0#
#1990000
1!
b10 &
b10 *
b10 -
b10 '
1#
#2000000
0#
#2010000
0!
b11 &
b11 *
b11 -
b11 '
1#
#2020000
0#
#2030000
b100 &
b100 *
b100 -
b100 '
1#
#2040000
0#
#2050000
1!
b101 &
b101 *
b101 -
b101 '
1#
#2060000
0#
#2070000
b110 &
b110 *
b110 -
b110 '
1#
#2080000
0#
#2090000
0!
b111 &
b111 *
b111 -
b111 '
1#
#2100000
0#
#2110000
b1000 &
b1000 *
b1000 -
b1000 '
1#
#2120000
0#
#2130000
b1001 &
b1001 *
b1001 -
b1001 '
1#
#2140000
0#
#2150000
1!
b1010 &
b1010 *
b1010 -
b1010 '
1#
#2160000
0#
#2170000
0!
b1011 &
b1011 *
b1011 -
b1011 '
1#
#2180000
0#
#2190000
b1100 &
b1100 *
b1100 -
b1100 '
1#
#2200000
0#
#2210000
b1101 &
b1101 *
b1101 -
b1101 '
1#
#2220000
0#
#2230000
b1110 &
b1110 *
b1110 -
b1110 '
1#
#2240000
0#
#2250000
1!
b1111 &
b1111 *
b1111 -
b1111 '
1#
#2260000
0#
#2270000
0!
b0 &
b0 *
b1001001101110101001000010010 $
b1001001101110101001000010010 )
b111 ,
b0 -
b0 '
1#
#2280000
0#
#2290000
1!
b1 &
b1 *
b1 -
b1 '
1#
#2300000
0#
#2310000
0!
b10 &
b10 *
b10 -
b10 '
1#
#2320000
0#
#2330000
b11 &
b11 *
b11 -
b11 '
1#
#2340000
0#
#2350000
1!
b100 &
b100 *
b100 -
b100 '
1#
#2360000
0#
#2370000
0!
b101 &
b101 *
b101 -
b101 '
1#
#2380000
0#
#2390000
b110 &
b110 *
b110 -
b110 '
1#
#2400000
0#
#2410000
b111 &
b111 *
b111 -
b111 '
1#
#2420000
0#
#2430000
b1000 &
b1000 *
b1000 -
b1000 '
1#
#2440000
0#
#2450000
1!
b1001 &
b1001 *
b1001 -
b1001 '
1#
#2460000
0#
#2470000
0!
b1010 &
b1010 *
b1010 -
b1010 '
1#
#2480000
0#
#2490000
b1011 &
b1011 *
b1011 -
b1011 '
1#
#2500000
0#
#2510000
1!
b1100 &
b1100 *
b1100 -
b1100 '
1#
#2520000
0#
#2530000
0!
b1101 &
b1101 *
b1101 -
b1101 '
1#
#2540000
0#
#2550000
1!
b1110 &
b1110 *
b1110 -
b1110 '
1#
#2560000
0#
#2570000
0!
b1111 &
b1111 *
b1111 -
b1111 '
1#
#2580000
0#
#2590000
1!
b0 &
b0 *
b10000000111100111110001100000001 $
b10000000111100111110001100000001 )
b1000 ,
b0 -
b0 '
1#
#2600000
0#
#2610000
0!
b1 &
b1 *
b1 -
b1 '
1#
#2620000
0#
#2630000
b10 &
b10 *
b10 -
b10 '
1#
#2640000
0#
#2650000
b11 &
b11 *
b11 -
b11 '
1#
#2660000
0#
#2670000
b100 &
b100 *
b100 -
b100 '
1#
#2680000
0#
#2690000
b101 &
b101 *
b101 -
b101 '
1#
#2700000
0#
#2710000
b110 &
b110 *
b110 -
b110 '
1#
#2720000
0#
#2730000
b111 &
b111 *
b111 -
b111 '
1#
#2740000
0#
#2750000
1!
b1000 &
b1000 *
b1000 -
b1000 '
1#
#2760000
0#
#2770000
b1001 &
b1001 *
b1001 -
b1001 '
1#
#2780000
0#
#2790000
0!
b1010 &
b1010 *
b1010 -
b1010 '
1#
#2800000
0#
#2810000
b1011 &
b1011 *
b1011 -
b1011 '
1#
#2820000
0#
#2830000
b1100 &
b1100 *
b1100 -
b1100 '
1#
#2840000
0#
#2850000
1!
b1101 &
b1101 *
b1101 -
b1101 '
1#
#2860000
0#
#2870000
b1110 &
b1110 *
b1110 -
b1110 '
1#
#2880000
0#
#2890000
b1111 &
b1111 *
b1111 -
b1111 '
1#
#2900000
0#
#2910000
b0 &
b0 *
b10000110110101111100110100001101 $
b10000110110101111100110100001101 )
b1001 ,
b0 -
b0 '
1#
#2920000
0#
#2930000
0!
b1 &
b1 *
b1 -
b1 '
1#
#2940000
0#
#2950000
1!
b10 &
b10 *
b10 -
b10 '
1#
#2960000
0#
#2970000
b11 &
b11 *
b11 -
b11 '
1#
#2980000
0#
#2990000
0!
b100 &
b100 *
b100 -
b100 '
1#
#3000000
0#
#3010000
b101 &
b101 *
b101 -
b101 '
1#
#3020000
0#
#3030000
b110 &
b110 *
b110 -
b110 '
1#
#3040000
0#
#3050000
b111 &
b111 *
b111 -
b111 '
1#
#3060000
0#
#3070000
1!
b1000 &
b1000 *
b1000 -
b1000 '
1#
#3080000
0#
#3090000
0!
b1001 &
b1001 *
b1001 -
b1001 '
1#
#3100000
0#
#3110000
1!
b1010 &
b1010 *
b1010 -
b1010 '
1#
#3120000
0#
#3130000
b1011 &
b1011 *
b1011 -
b1011 '
1#
#3140000
0#
#3150000
0!
b1100 &
b1100 *
b1100 -
b1100 '
1#
#3160000
0#
#3170000
b1101 &
b1101 *
b1101 -
b1101 '
1#
#3180000
0#
#3190000
1!
b1110 &
b1110 *
b1110 -
b1110 '
1#
#3200000
0#
#3210000
b1111 &
b1111 *
b1111 -
b1111 '
1#
#3220000
0#
#3230000
0!
b0 &
b0 *
b10111011001000111111000101110110 $
b10111011001000111111000101110110 )
b1010 ,
b0 -
b0 '
1#
#3240000
0#
#3250000
1!
b1 &
b1 *
b1 -
b1 '
1#
#3260000
0#
#3270000
b10 &
b10 *
b10 -
b10 '
1#
#3280000
0#
#3290000
0!
b11 &
b11 *
b11 -
b11 '
1#
#3300000
0#
#3310000
1!
b100 &
b100 *
b100 -
b100 '
1#
#3320000
0#
#3330000
b101 &
b101 *
b101 -
b101 '
1#
#3340000
0#
#3350000
b110 &
b110 *
b110 -
b110 '
1#
#3360000
0#
#3370000
0!
b111 &
b111 *
b111 -
b111 '
1#
#3380000
0#
#3390000
1!
b1000 &
b1000 *
b1000 -
b1000 '
1#
#3400000
0#
#3410000
0!
b1001 &
b1001 *
b1001 -
b1001 '
1#
#3420000
0#
#3430000
b1010 &
b1010 *
b1010 -
b1010 '
1#
#3440000
0#
#3450000
b1011 &
b1011 *
b1011 -
b1011 '
1#
#3460000
0#
#3470000
1!
b1100 &
b1100 *
b1100 -
b1100 '
1#
#3480000
0#
#3490000
b1101 &
b1101 *
b1101 -
b1101 '
1#
#3500000
0#
#3510000
b1110 &
b1110 *
b1110 -
b1110 '
1#
#3520000
0#
#3530000
b1111 &
b1111 *
b1111 -
b1111 '
1#
#3540000
0#
#3550000
b0 &
b0 *
b10011110100011011100110100111101 $
b10011110100011011100110100111101 )
b1011 ,
b0 -
b0 '
1#
#3560000
0#
#3570000
0!
b1 &
b1 *
b1 -
b1 '
1#
#3580000
0#
#3590000
1!
b10 &
b10 *
b10 -
b10 '
1#
#3600000
0#
#3610000
b11 &
b11 *
b11 -
b11 '
1#
#3620000
0#
#3630000
b100 &
b100 *
b100 -
b100 '
1#
#3640000
0#
#3650000
b101 &
b101 *
b101 -
b101 '
1#
#3660000
0#
#3670000
0!
b110 &
b110 *
b110 -
b110 '
1#
#3680000
0#
#3690000
b111 &
b111 *
b111 -
b111 '
1#
#3700000
0#
#3710000
1!
b1000 &
b1000 *
b1000 -
b1000 '
1#
#3720000
0#
#3730000
0!
b1001 &
b1001 *
b1001 -
b1001 '
1#
#3740000
0#
#3750000
1!
b1010 &
b1010 *
b1010 -
b1010 '
1#
#3760000
0#
#3770000
b1011 &
b1011 *
b1011 -
b1011 '
1#
#3780000
0#
#3790000
0!
b1100 &
b1100 *
b1100 -
b1100 '
1#
#3800000
0#
#3810000
b1101 &
b1101 *
b1101 -
b1101 '
1#
#3820000
0#
#3830000
1!
b1110 &
b1110 *
b1110 -
b1110 '
1#
#3840000
0#
#3850000
b1111 &
b1111 *
b1111 -
b1111 '
1#
#3860000
0#
#3870000
b0 &
b0 *
b11110110110101000101011111101101 $
b11110110110101000101011111101101 )
b1100 ,
b0 -
b0 '
1#
#3880000
0#
#3890000
0!
b1 &
b1 *
b1 -
b1 '
1#
#3900000
0#
#3910000
1!
b10 &
b10 *
b10 -
b10 '
1#
#3920000
0#
#3930000
b11 &
b11 *
b11 -
b11 '
1#
#3940000
0#
#3950000
0!
b100 &
b100 *
b100 -
b100 '
1#
#3960000
0#
#3970000
1!
b101 &
b101 *
b101 -
b101 '
1#
#3980000
0#
#3990000
b110 &
b110 *
b110 -
b110 '
1#
#4000000
0#
#4010000
b111 &
b111 *
b111 -
b111 '
1#
#4020000
0#
#4030000
b1000 &
b1000 *
b1000 -
b1000 '
1#
#4040000
0#
#4050000
b1001 &
b1001 *
b1001 -
b1001 '
1#
#4060000
0#
#4070000
b1010 &
b1010 *
b1010 -
b1010 '
1#
#4080000
0#
#4090000
0!
b1011 &
b1011 *
b1011 -
b1011 '
1#
#4100000
0#
#4110000
1!
b1100 &
b1100 *
b1100 -
b1100 '
1#
#4120000
0#
#4130000
0!
b1101 &
b1101 *
b1101 -
b1101 '
1#
#4140000
0#
#4150000
1!
b1110 &
b1110 *
b1110 -
b1110 '
1#
#4160000
0#
#4170000
0!
b1111 &
b1111 *
b1111 -
b1111 '
1#
#4180000
0#
#4190000
b0 &
b0 *
b11000110001011011111011110001100 $
b11000110001011011111011110001100 )
b1101 ,
b0 -
b0 '
1#
#4200000
0#
#4210000
b1 &
b1 *
b1 -
b1 '
1#
#4220000
0#
#4230000
1!
b10 &
b10 *
b10 -
b10 '
1#
#4240000
0#
#4250000
b11 &
b11 *
b11 -
b11 '
1#
#4260000
0#
#4270000
0!
b100 &
b100 *
b100 -
b100 '
1#
#4280000
0#
#4290000
b101 &
b101 *
b101 -
b101 '
1#
#4300000
0#
#4310000
b110 &
b110 *
b110 -
b110 '
1#
#4320000
0#
#4330000
1!
b111 &
b111 *
b111 -
b111 '
1#
#4340000
0#
#4350000
b1000 &
b1000 *
b1000 -
b1000 '
1#
#4360000
0#
#4370000
b1001 &
b1001 *
b1001 -
b1001 '
1#
#4380000
0#
#4390000
b1010 &
b1010 *
b1010 -
b1010 '
1#
#4400000
0#
#4410000
0!
b1011 &
b1011 *
b1011 -
b1011 '
1#
#4420000
0#
#4430000
1!
b1100 &
b1100 *
b1100 -
b1100 '
1#
#4440000
0#
#4450000
b1101 &
b1101 *
b1101 -
b1101 '
1#
#4460000
0#
#4470000
b1110 &
b1110 *
b1110 -
b1110 '
1#
#4480000
0#
#4490000
b1111 &
b1111 *
b1111 -
b1111 '
1#
#4500000
0#
#4510000
b0 &
b0 *
b11111100111111011110100111111001 $
b11111100111111011110100111111001 )
b1110 ,
b0 -
b0 '
1#
#4520000
0#
#4530000
0!
b1 &
b1 *
b1 -
b1 '
1#
#4540000
0#
#4550000
b10 &
b10 *
b10 -
b10 '
1#
#4560000
0#
#4570000
1!
b11 &
b11 *
b11 -
b11 '
1#
#4580000
0#
#4590000
b100 &
b100 *
b100 -
b100 '
1#
#4600000
0#
#4610000
b101 &
b101 *
b101 -
b101 '
1#
#4620000
0#
#4630000
b110 &
b110 *
b110 -
b110 '
1#
#4640000
0#
#4650000
b111 &
b111 *
b111 -
b111 '
1#
#4660000
0#
#4670000
b1000 &
b1000 *
b1000 -
b1000 '
1#
#4680000
0#
#4690000
0!
b1001 &
b1001 *
b1001 -
b1001 '
1#
#4700000
0#
#4710000
b1010 &
b1010 *
b1010 -
b1010 '
1#
#4720000
0#
#4730000
1!
b1011 &
b1011 *
b1011 -
b1011 '
1#
#4740000
0#
#4750000
0!
b1100 &
b1100 *
b1100 -
b1100 '
1#
#4760000
0#
#4770000
1!
b1101 &
b1101 *
b1101 -
b1101 '
1#
#4780000
0#
#4790000
b1110 &
b1110 *
b1110 -
b1110 '
1#
#4800000
0#
#4810000
b1111 &
b1111 *
b1111 -
b1111 '
1#
#4820000
0#
#4830000
0!
b0 &
b0 *
b1100011001101110010010011000110 $
b1100011001101110010010011000110 )
b1111 ,
b0 -
b0 '
1#
#4840000
0#
#4850000
1!
b1 &
b1 *
b1 -
b1 '
1#
#4860000
0#
#4870000
b10 &
b10 *
b10 -
b10 '
1#
#4880000
0#
#4890000
0!
b11 &
b11 *
b11 -
b11 '
1#
#4900000
0#
#4910000
b100 &
b100 *
b100 -
b100 '
1#
#4920000
0#
#4930000
b101 &
b101 *
b101 -
b101 '
1#
#4940000
0#
#4950000
1!
b110 &
b110 *
b110 -
b110 '
1#
#4960000
0#
#4970000
b111 &
b111 *
b111 -
b111 '
1#
#4980000
0#
#4990000
0!
b1000 &
b1000 *
b1000 -
b1000 '
1#
#5000000
0#
#5010000
b1001 &
b1001 *
b1001 -
b1001 '
1#
#5020000
0#
#5030000
1!
b1010 &
b1010 *
b1010 -
b1010 '
1#
#5040000
0#
#5050000
0!
b1011 &
b1011 *
b1011 -
b1011 '
1#
#5060000
0#
#5070000
b1100 &
b1100 *
b1100 -
b1100 '
1#
#5080000
0#
#5090000
1!
b1101 &
b1101 *
b1101 -
b1101 '
1#
#5100000
0#
#5110000
0!
b1110 &
b1110 *
b1110 -
b1110 '
1#
#5120000
0#
#5130000
b1111 &
b1111 *
b1111 -
b1111 '
1#
#5140000
0#
#5150000
1!
b0 &
b0 *
b1100010111101111000010011000101 $
b1100010111101111000010011000101 )
b10000 ,
b0 -
b0 '
1#
#5160000
0#
#5170000
0!
b1 &
b1 *
b1 -
b1 '
1#
#5180000
0#
#5190000
1!
b10 &
b10 *
b10 -
b10 '
1#
#5200000
0#
#5210000
0!
b11 &
b11 *
b11 -
b11 '
1#
#5220000
0#
#5230000
b100 &
b100 *
b100 -
b100 '
1#
#5240000
0#
#5250000
b101 &
b101 *
b101 -
b101 '
1#
#5260000
0#
#5270000
1!
b110 &
b110 *
b110 -
b110 '
1#
#5280000
0#
#5290000
b111 &
b111 *
b111 -
b111 '
1#
#5300000
0#
#5310000
0!
b1000 &
b1000 *
b1000 -
b1000 '
1#
#5320000
0#
#5330000
b1001 &
b1001 *
b1001 -
b1001 '
1#
#5340000
0#
#5350000
1!
b1010 &
b1010 *
b1010 -
b1010 '
1#
#5360000
0#
#5370000
0!
b1011 &
b1011 *
b1011 -
b1011 '
1#
#5380000
0#
#5390000
b1100 &
b1100 *
b1100 -
b1100 '
1#
#5400000
0#
#5410000
b1101 &
b1101 *
b1101 -
b1101 '
1#
#5420000
0#
#5430000
b1110 &
b1110 *
b1110 -
b1110 '
1#
#5440000
0#
#5450000
1!
b1111 &
b1111 *
b1111 -
b1111 '
1#
#5460000
0#
#5470000
0!
b0 &
b0 *
b1010101000100111101001010101010 $
b1010101000100111101001010101010 )
b10001 ,
b0 -
b0 '
1#
#5480000
0#
#5490000
1!
b1 &
b1 *
b1 -
b1 '
1#
#5500000
0#
#5510000
0!
b10 &
b10 *
b10 -
b10 '
1#
#5520000
0#
#5530000
1!
b11 &
b11 *
b11 -
b11 '
1#
#5540000
0#
#5550000
0!
b100 &
b100 *
b100 -
b100 '
1#
#5560000
0#
#5570000
1!
b101 &
b101 *
b101 -
b101 '
1#
#5580000
0#
#5590000
0!
b110 &
b110 *
b110 -
b110 '
1#
#5600000
0#
#5610000
1!
b111 &
b111 *
b111 -
b111 '
1#
#5620000
0#
#5630000
0!
b1000 &
b1000 *
b1000 -
b1000 '
1#
#5640000
0#
#5650000
1!
b1001 &
b1001 *
b1001 -
b1001 '
1#
#5660000
0#
#5670000
0!
b1010 &
b1010 *
b1010 -
b1010 '
1#
#5680000
0#
#5690000
b1011 &
b1011 *
b1011 -
b1011 '
1#
#5700000
0#
#5710000
1!
b1100 &
b1100 *
b1100 -
b1100 '
1#
#5720000
0#
#5730000
0!
b1101 &
b1101 *
b1101 -
b1101 '
1#
#5740000
0#
#5750000
1!
b1110 &
b1110 *
b1110 -
b1110 '
1#
#5760000
0#
#5770000
b1111 &
b1111 *
b1111 -
b1111 '
1#
#5780000
0#
#5790000
b0 &
b0 *
b11110010101011111111011111100101 $
b11110010101011111111011111100101 )
b10010 ,
b0 -
b0 '
1#
#5800000
0#
#5810000
0!
b1 &
b1 *
b1 -
b1 '
1#
#5820000
0#
#5830000
1!
b10 &
b10 *
b10 -
b10 '
1#
#5840000
0#
#5850000
0!
b11 &
b11 *
b11 -
b11 '
1#
#5860000
0#
#5870000
b100 &
b100 *
b100 -
b100 '
1#
#5880000
0#
#5890000
1!
b101 &
b101 *
b101 -
b101 '
1#
#5900000
0#
#5910000
b110 &
b110 *
b110 -
b110 '
1#
#5920000
0#
#5930000
b111 &
b111 *
b111 -
b111 '
1#
#5940000
0#
#5950000
b1000 &
b1000 *
b1000 -
b1000 '
1#
#5960000
0#
#5970000
b1001 &
b1001 *
b1001 -
b1001 '
1#
#5980000
0#
#5990000
b1010 &
b1010 *
b1010 -
b1010 '
1#
#6000000
0#
#6010000
0!
b1011 &
b1011 *
b1011 -
b1011 '
1#
#6020000
0#
#6030000
1!
b1100 &
b1100 *
b1100 -
b1100 '
1#
#6040000
0#
#6050000
b1101 &
b1101 *
b1101 -
b1101 '
1#
#6060000
0#
#6070000
b1110 &
b1110 *
b1110 -
b1110 '
1#
#6080000
0#
#6090000
b1111 &
b1111 *
b1111 -
b1111 '
1#
#6100000
0#
#6110000
b0 &
b0 *
b111011110100100111001001110111 $
b111011110100100111001001110111 )
b10011 ,
b0 -
b0 '
1#
#6120000
0#
#6130000
b1 &
b1 *
b1 -
b1 '
1#
#6140000
0#
#6150000
b10 &
b10 *
b10 -
b10 '
1#
#6160000
0#
#6170000
0!
b11 &
b11 *
b11 -
b11 '
1#
#6180000
0#
#6190000
1!
b100 &
b100 *
b100 -
b100 '
1#
#6200000
0#
#6210000
b101 &
b101 *
b101 -
b101 '
1#
#6220000
0#
#6230000
b110 &
b110 *
b110 -
b110 '
1#
#6240000
0#
#6250000
0!
b111 &
b111 *
b111 -
b111 '
1#
#6260000
0#
#6270000
b1000 &
b1000 *
b1000 -
b1000 '
1#
#6280000
0#
#6290000
1!
b1001 &
b1001 *
b1001 -
b1001 '
1#
#6300000
0#
#6310000
0!
b1010 &
b1010 *
b1010 -
b1010 '
1#
#6320000
0#
#6330000
b1011 &
b1011 *
b1011 -
b1011 '
1#
#6340000
0#
#6350000
1!
b1100 &
b1100 *
b1100 -
b1100 '
1#
#6360000
0#
#6370000
b1101 &
b1101 *
b1101 -
b1101 '
1#
#6380000
0#
#6390000
b1110 &
b1110 *
b1110 -
b1110 '
1#
#6400000
0#
#6410000
0!
b1111 &
b1111 *
b1111 -
b1111 '
1#
#6420000
0#
#6430000
b0 &
b0 *
b1001001100101101011000010010 $
b1001001100101101011000010010 )
b10100 ,
b0 -
b0 '
1#
#6440000
0#
#6450000
1!
b1 &
b1 *
b1 -
b1 '
1#
#6460000
0#
#6470000
0!
b10 &
b10 *
b10 -
b10 '
1#
#6480000
0#
#6490000
b11 &
b11 *
b11 -
b11 '
1#
#6500000
0#
#6510000
1!
b100 &
b100 *
b100 -
b100 '
1#
#6520000
0#
